[
  {
    "ANNO": 1996,
    "CODICE_MESE": 1,
    "NOME_MESE": "Gennaio",
    "CODICE_PRODOTTO": 1,
    "NOME_PRODOTTO": "Benzina",
    "PREZZO": "904.18",
    "IVA": "144.37",
    "ACCISA": "525.77",
    "NETTO": "234.05"
  },
  {
    "ANNO": 1996,
    "CODICE_MESE": 2,
    "NOME_MESE": "Febbraio",
    "CODICE_PRODOTTO": 1,
    "NOME_PRODOTTO": "Benzina",
    "PREZZO": "907.09",
    "IVA": "144.83",
    "ACCISA": "527.96",
    "NETTO": "234.3"
  },
  {
    "ANNO": 1996,
    "CODICE_MESE": 3,
    "NOME_MESE": "Marzo",
    "CODICE_PRODOTTO": 1,
    "NOME_PRODOTTO": "Benzina",
    "PREZZO": "917.83",
    "IVA": "146.54",
    "ACCISA": "527.96",
    "NETTO": "243.32"
  },
  {
    "ANNO": 1996,
    "CODICE_MESE": 4,
    "NOME_MESE": "Aprile",
    "CODICE_PRODOTTO": 1,
    "NOME_PRODOTTO": "Benzina",
    "PREZZO": "931.48",
    "IVA": "148.72",
    "ACCISA": "527.96",
    "NETTO": "254.79"
  },
  {
    "ANNO": 1996,
    "CODICE_MESE": 5,
    "NOME_MESE": "Maggio",
    "CODICE_PRODOTTO": 1,
    "NOME_PRODOTTO": "Benzina",
    "PREZZO": "929.94",
    "IVA": "148.48",
    "ACCISA": "527.96",
    "NETTO": "253.5"
  },
  {
    "ANNO": 1996,
    "CODICE_MESE": 6,
    "NOME_MESE": "Giugno",
    "CODICE_PRODOTTO": 1,
    "NOME_PRODOTTO": "Benzina",
    "PREZZO": "924.06",
    "IVA": "147.54",
    "ACCISA": "527.96",
    "NETTO": "248.56"
  },
  {
    "ANNO": 1996,
    "CODICE_MESE": 7,
    "NOME_MESE": "Luglio",
    "CODICE_PRODOTTO": 1,
    "NOME_PRODOTTO": "Benzina",
    "PREZZO": "924.72",
    "IVA": "147.65",
    "ACCISA": "527.96",
    "NETTO": "249.11"
  },
  {
    "ANNO": 1996,
    "CODICE_MESE": 8,
    "NOME_MESE": "Agosto",
    "CODICE_PRODOTTO": 1,
    "NOME_PRODOTTO": "Benzina",
    "PREZZO": "926.01",
    "IVA": "147.85",
    "ACCISA": "527.96",
    "NETTO": "250.19"
  },
  {
    "ANNO": 1996,
    "CODICE_MESE": 9,
    "NOME_MESE": "Settembre",
    "CODICE_PRODOTTO": 1,
    "NOME_PRODOTTO": "Benzina",
    "PREZZO": "926.39",
    "IVA": "147.91",
    "ACCISA": "527.96",
    "NETTO": "250.51"
  },
  {
    "ANNO": 1996,
    "CODICE_MESE": 10,
    "NOME_MESE": "Ottobre",
    "CODICE_PRODOTTO": 1,
    "NOME_PRODOTTO": "Benzina",
    "PREZZO": "929.26",
    "IVA": "148.37",
    "ACCISA": "527.96",
    "NETTO": "252.92"
  },
  {
    "ANNO": 1996,
    "CODICE_MESE": 11,
    "NOME_MESE": "Novembre",
    "CODICE_PRODOTTO": 1,
    "NOME_PRODOTTO": "Benzina",
    "PREZZO": "939.44",
    "IVA": "149.99",
    "ACCISA": "527.96",
    "NETTO": "261.48"
  },
  {
    "ANNO": 1996,
    "CODICE_MESE": 12,
    "NOME_MESE": "Dicembre",
    "CODICE_PRODOTTO": 1,
    "NOME_PRODOTTO": "Benzina",
    "PREZZO": "936.32",
    "IVA": "149.5",
    "ACCISA": "527.96",
    "NETTO": "258.86"
  },
  {
    "ANNO": 1997,
    "CODICE_MESE": 1,
    "NOME_MESE": "Gennaio",
    "CODICE_PRODOTTO": 1,
    "NOME_PRODOTTO": "Benzina",
    "PREZZO": "938.82",
    "IVA": "149.9",
    "ACCISA": "527.96",
    "NETTO": "260.96"
  },
  {
    "ANNO": 1997,
    "CODICE_MESE": 2,
    "NOME_MESE": "Febbraio",
    "CODICE_PRODOTTO": 1,
    "NOME_PRODOTTO": "Benzina",
    "PREZZO": "942.26",
    "IVA": "150.45",
    "ACCISA": "527.96",
    "NETTO": "263.85"
  },
  {
    "ANNO": 1997,
    "CODICE_MESE": 3,
    "NOME_MESE": "Marzo",
    "CODICE_PRODOTTO": 1,
    "NOME_PRODOTTO": "Benzina",
    "PREZZO": "944.48",
    "IVA": "150.8",
    "ACCISA": "527.96",
    "NETTO": "265.72"
  },
  {
    "ANNO": 1997,
    "CODICE_MESE": 4,
    "NOME_MESE": "Aprile",
    "CODICE_PRODOTTO": 1,
    "NOME_PRODOTTO": "Benzina",
    "PREZZO": "939.78",
    "IVA": "150.05",
    "ACCISA": "527.96",
    "NETTO": "261.77"
  },
  {
    "ANNO": 1997,
    "CODICE_MESE": 5,
    "NOME_MESE": "Maggio",
    "CODICE_PRODOTTO": 1,
    "NOME_PRODOTTO": "Benzina",
    "PREZZO": "939.35",
    "IVA": "149.98",
    "ACCISA": "527.96",
    "NETTO": "261.41"
  },
  {
    "ANNO": 1997,
    "CODICE_MESE": 6,
    "NOME_MESE": "Giugno",
    "CODICE_PRODOTTO": 1,
    "NOME_PRODOTTO": "Benzina",
    "PREZZO": "940.8",
    "IVA": "150.21",
    "ACCISA": "527.96",
    "NETTO": "262.62"
  },
  {
    "ANNO": 1997,
    "CODICE_MESE": 7,
    "NOME_MESE": "Luglio",
    "CODICE_PRODOTTO": 1,
    "NOME_PRODOTTO": "Benzina",
    "PREZZO": "939.19",
    "IVA": "149.95",
    "ACCISA": "527.96",
    "NETTO": "261.27"
  },
  {
    "ANNO": 1997,
    "CODICE_MESE": 8,
    "NOME_MESE": "Agosto",
    "CODICE_PRODOTTO": 1,
    "NOME_PRODOTTO": "Benzina",
    "PREZZO": "947.07",
    "IVA": "151.21",
    "ACCISA": "527.96",
    "NETTO": "267.89"
  },
  {
    "ANNO": 1997,
    "CODICE_MESE": 9,
    "NOME_MESE": "Settembre",
    "CODICE_PRODOTTO": 1,
    "NOME_PRODOTTO": "Benzina",
    "PREZZO": "945.2",
    "IVA": "150.91",
    "ACCISA": "527.96",
    "NETTO": "266.33"
  },
  {
    "ANNO": 1997,
    "CODICE_MESE": 10,
    "NOME_MESE": "Ottobre",
    "CODICE_PRODOTTO": 1,
    "NOME_PRODOTTO": "Benzina",
    "PREZZO": "947.57",
    "IVA": "156.86",
    "ACCISA": "527.96",
    "NETTO": "262.74"
  },
  {
    "ANNO": 1997,
    "CODICE_MESE": 11,
    "NOME_MESE": "Novembre",
    "CODICE_PRODOTTO": 1,
    "NOME_PRODOTTO": "Benzina",
    "PREZZO": "946.48",
    "IVA": "157.75",
    "ACCISA": "527.96",
    "NETTO": "260.77"
  },
  {
    "ANNO": 1997,
    "CODICE_MESE": 12,
    "NOME_MESE": "Dicembre",
    "CODICE_PRODOTTO": 1,
    "NOME_PRODOTTO": "Benzina",
    "PREZZO": "935.79",
    "IVA": "155.96",
    "ACCISA": "527.96",
    "NETTO": "251.86"
  },
  {
    "ANNO": 1998,
    "CODICE_MESE": 1,
    "NOME_MESE": "Gennaio",
    "CODICE_PRODOTTO": 1,
    "NOME_PRODOTTO": "Benzina",
    "PREZZO": "930.69",
    "IVA": "155.11",
    "ACCISA": "527.96",
    "NETTO": "247.61"
  },
  {
    "ANNO": 1998,
    "CODICE_MESE": 2,
    "NOME_MESE": "Febbraio",
    "CODICE_PRODOTTO": 1,
    "NOME_PRODOTTO": "Benzina",
    "PREZZO": "925.88",
    "IVA": "154.31",
    "ACCISA": "527.96",
    "NETTO": "243.6"
  },
  {
    "ANNO": 1998,
    "CODICE_MESE": 3,
    "NOME_MESE": "Marzo",
    "CODICE_PRODOTTO": 1,
    "NOME_PRODOTTO": "Benzina",
    "PREZZO": "912.41",
    "IVA": "152.07",
    "ACCISA": "527.96",
    "NETTO": "232.38"
  },
  {
    "ANNO": 1998,
    "CODICE_MESE": 4,
    "NOME_MESE": "Aprile",
    "CODICE_PRODOTTO": 1,
    "NOME_PRODOTTO": "Benzina",
    "PREZZO": "908.6",
    "IVA": "151.43",
    "ACCISA": "527.96",
    "NETTO": "229.2"
  },
  {
    "ANNO": 1998,
    "CODICE_MESE": 5,
    "NOME_MESE": "Maggio",
    "CODICE_PRODOTTO": 1,
    "NOME_PRODOTTO": "Benzina",
    "PREZZO": "912.36",
    "IVA": "152.06",
    "ACCISA": "527.96",
    "NETTO": "232.34"
  },
  {
    "ANNO": 1998,
    "CODICE_MESE": 6,
    "NOME_MESE": "Giugno",
    "CODICE_PRODOTTO": 1,
    "NOME_PRODOTTO": "Benzina",
    "PREZZO": "912.03",
    "IVA": "152.01",
    "ACCISA": "527.96",
    "NETTO": "232.06"
  },
  {
    "ANNO": 1998,
    "CODICE_MESE": 7,
    "NOME_MESE": "Luglio",
    "CODICE_PRODOTTO": 1,
    "NOME_PRODOTTO": "Benzina",
    "PREZZO": "913.33",
    "IVA": "152.22",
    "ACCISA": "527.96",
    "NETTO": "233.14"
  },
  {
    "ANNO": 1998,
    "CODICE_MESE": 8,
    "NOME_MESE": "Agosto",
    "CODICE_PRODOTTO": 1,
    "NOME_PRODOTTO": "Benzina",
    "PREZZO": "909.71",
    "IVA": "151.62",
    "ACCISA": "527.96",
    "NETTO": "230.13"
  },
  {
    "ANNO": 1998,
    "CODICE_MESE": 9,
    "NOME_MESE": "Settembre",
    "CODICE_PRODOTTO": 1,
    "NOME_PRODOTTO": "Benzina",
    "PREZZO": "906.38",
    "IVA": "151.06",
    "ACCISA": "527.96",
    "NETTO": "227.35"
  },
  {
    "ANNO": 1998,
    "CODICE_MESE": 10,
    "NOME_MESE": "Ottobre",
    "CODICE_PRODOTTO": 1,
    "NOME_PRODOTTO": "Benzina",
    "PREZZO": "904.22",
    "IVA": "150.7",
    "ACCISA": "527.96",
    "NETTO": "225.55"
  },
  {
    "ANNO": 1998,
    "CODICE_MESE": 11,
    "NOME_MESE": "Novembre",
    "CODICE_PRODOTTO": 1,
    "NOME_PRODOTTO": "Benzina",
    "PREZZO": "897.64",
    "IVA": "149.61",
    "ACCISA": "527.96",
    "NETTO": "220.07"
  },
  {
    "ANNO": 1998,
    "CODICE_MESE": 12,
    "NOME_MESE": "Dicembre",
    "CODICE_PRODOTTO": 1,
    "NOME_PRODOTTO": "Benzina",
    "PREZZO": "885.21",
    "IVA": "147.54",
    "ACCISA": "527.96",
    "NETTO": "209.71"
  },
  {
    "ANNO": 1999,
    "CODICE_MESE": 1,
    "NOME_MESE": "Gennaio",
    "CODICE_PRODOTTO": 1,
    "NOME_PRODOTTO": "Benzina",
    "PREZZO": "885.59",
    "IVA": "147.6",
    "ACCISA": "534.23",
    "NETTO": "203.76"
  },
  {
    "ANNO": 1999,
    "CODICE_MESE": 2,
    "NOME_MESE": "Febbraio",
    "CODICE_PRODOTTO": 1,
    "NOME_PRODOTTO": "Benzina",
    "PREZZO": "893.47",
    "IVA": "148.91",
    "ACCISA": "541.84",
    "NETTO": "202.72"
  },
  {
    "ANNO": 1999,
    "CODICE_MESE": 3,
    "NOME_MESE": "Marzo",
    "CODICE_PRODOTTO": 1,
    "NOME_PRODOTTO": "Benzina",
    "PREZZO": "905.33",
    "IVA": "150.89",
    "ACCISA": "541.84",
    "NETTO": "212.6"
  },
  {
    "ANNO": 1999,
    "CODICE_MESE": 4,
    "NOME_MESE": "Aprile",
    "CODICE_PRODOTTO": 1,
    "NOME_PRODOTTO": "Benzina",
    "PREZZO": "934.12",
    "IVA": "155.69",
    "ACCISA": "541.84",
    "NETTO": "236.59"
  },
  {
    "ANNO": 1999,
    "CODICE_MESE": 5,
    "NOME_MESE": "Maggio",
    "CODICE_PRODOTTO": 1,
    "NOME_PRODOTTO": "Benzina",
    "PREZZO": "949.7",
    "IVA": "158.28",
    "ACCISA": "541.84",
    "NETTO": "249.57"
  },
  {
    "ANNO": 1999,
    "CODICE_MESE": 6,
    "NOME_MESE": "Giugno",
    "CODICE_PRODOTTO": 1,
    "NOME_PRODOTTO": "Benzina",
    "PREZZO": "949.06",
    "IVA": "158.18",
    "ACCISA": "541.84",
    "NETTO": "249.04"
  },
  {
    "ANNO": 1999,
    "CODICE_MESE": 7,
    "NOME_MESE": "Luglio",
    "CODICE_PRODOTTO": 1,
    "NOME_PRODOTTO": "Benzina",
    "PREZZO": "969.96",
    "IVA": "161.66",
    "ACCISA": "541.84",
    "NETTO": "266.45"
  },
  {
    "ANNO": 1999,
    "CODICE_MESE": 8,
    "NOME_MESE": "Agosto",
    "CODICE_PRODOTTO": 1,
    "NOME_PRODOTTO": "Benzina",
    "PREZZO": "982.52",
    "IVA": "163.75",
    "ACCISA": "541.84",
    "NETTO": "276.92"
  },
  {
    "ANNO": 1999,
    "CODICE_MESE": 9,
    "NOME_MESE": "Settembre",
    "CODICE_PRODOTTO": 1,
    "NOME_PRODOTTO": "Benzina",
    "PREZZO": "995.44",
    "IVA": "165.91",
    "ACCISA": "541.84",
    "NETTO": "287.69"
  },
  {
    "ANNO": 1999,
    "CODICE_MESE": 10,
    "NOME_MESE": "Ottobre",
    "CODICE_PRODOTTO": 1,
    "NOME_PRODOTTO": "Benzina",
    "PREZZO": "998.54",
    "IVA": "166.43",
    "ACCISA": "541.84",
    "NETTO": "290.28"
  },
  {
    "ANNO": 1999,
    "CODICE_MESE": 11,
    "NOME_MESE": "Novembre",
    "CODICE_PRODOTTO": 1,
    "NOME_PRODOTTO": "Benzina",
    "PREZZO": "986.35",
    "IVA": "164.39",
    "ACCISA": "528.93",
    "NETTO": "293.02"
  },
  {
    "ANNO": 1999,
    "CODICE_MESE": 12,
    "NOME_MESE": "Dicembre",
    "CODICE_PRODOTTO": 1,
    "NOME_PRODOTTO": "Benzina",
    "PREZZO": "1010.62",
    "IVA": "168.44",
    "ACCISA": "528.93",
    "NETTO": "313.25"
  },
  {
    "ANNO": 2000,
    "CODICE_MESE": 1,
    "NOME_MESE": "Gennaio",
    "CODICE_PRODOTTO": 1,
    "NOME_PRODOTTO": "Benzina",
    "PREZZO": "1008.17",
    "IVA": "168.03",
    "ACCISA": "527.4",
    "NETTO": "312.74"
  },
  {
    "ANNO": 2000,
    "CODICE_MESE": 2,
    "NOME_MESE": "Febbraio",
    "CODICE_PRODOTTO": 1,
    "NOME_PRODOTTO": "Benzina",
    "PREZZO": "1021.43",
    "IVA": "170.24",
    "ACCISA": "526.78",
    "NETTO": "324.41"
  },
  {
    "ANNO": 2000,
    "CODICE_MESE": 3,
    "NOME_MESE": "Marzo",
    "CODICE_PRODOTTO": 1,
    "NOME_PRODOTTO": "Benzina",
    "PREZZO": "1059.34",
    "IVA": "176.56",
    "ACCISA": "524.28",
    "NETTO": "358.5"
  },
  {
    "ANNO": 2000,
    "CODICE_MESE": 4,
    "NOME_MESE": "Aprile",
    "CODICE_PRODOTTO": 1,
    "NOME_PRODOTTO": "Benzina",
    "PREZZO": "1046.93",
    "IVA": "174.49",
    "ACCISA": "520.32",
    "NETTO": "352.12"
  },
  {
    "ANNO": 2000,
    "CODICE_MESE": 5,
    "NOME_MESE": "Maggio",
    "CODICE_PRODOTTO": 1,
    "NOME_PRODOTTO": "Benzina",
    "PREZZO": "1066.23",
    "IVA": "177.71",
    "ACCISA": "520.32",
    "NETTO": "368.2"
  },
  {
    "ANNO": 2000,
    "CODICE_MESE": 6,
    "NOME_MESE": "Giugno",
    "CODICE_PRODOTTO": 1,
    "NOME_PRODOTTO": "Benzina",
    "PREZZO": "1107.3",
    "IVA": "184.55",
    "ACCISA": "520.32",
    "NETTO": "402.43"
  },
  {
    "ANNO": 2000,
    "CODICE_MESE": 7,
    "NOME_MESE": "Luglio",
    "CODICE_PRODOTTO": 1,
    "NOME_PRODOTTO": "Benzina",
    "PREZZO": "1118.13",
    "IVA": "186.35",
    "ACCISA": "520.32",
    "NETTO": "411.45"
  },
  {
    "ANNO": 2000,
    "CODICE_MESE": 8,
    "NOME_MESE": "Agosto",
    "CODICE_PRODOTTO": 1,
    "NOME_PRODOTTO": "Benzina",
    "PREZZO": "1100.1",
    "IVA": "183.35",
    "ACCISA": "520.32",
    "NETTO": "396.43"
  },
  {
    "ANNO": 2000,
    "CODICE_MESE": 9,
    "NOME_MESE": "Settembre",
    "CODICE_PRODOTTO": 1,
    "NOME_PRODOTTO": "Benzina",
    "PREZZO": "1117.94",
    "IVA": "186.32",
    "ACCISA": "520.32",
    "NETTO": "411.29"
  },
  {
    "ANNO": 2000,
    "CODICE_MESE": 10,
    "NOME_MESE": "Ottobre",
    "CODICE_PRODOTTO": 1,
    "NOME_PRODOTTO": "Benzina",
    "PREZZO": "1114.66",
    "IVA": "185.78",
    "ACCISA": "520.32",
    "NETTO": "408.56"
  },
  {
    "ANNO": 2000,
    "CODICE_MESE": 11,
    "NOME_MESE": "Novembre",
    "CODICE_PRODOTTO": 1,
    "NOME_PRODOTTO": "Benzina",
    "PREZZO": "1117.27",
    "IVA": "186.21",
    "ACCISA": "520.32",
    "NETTO": "410.73"
  },
  {
    "ANNO": 2000,
    "CODICE_MESE": 12,
    "NOME_MESE": "Dicembre",
    "CODICE_PRODOTTO": 1,
    "NOME_PRODOTTO": "Benzina",
    "PREZZO": "1091.29",
    "IVA": "181.88",
    "ACCISA": "520.32",
    "NETTO": "389.09"
  },
  {
    "ANNO": 2001,
    "CODICE_MESE": 1,
    "NOME_MESE": "Gennaio",
    "CODICE_PRODOTTO": 1,
    "NOME_PRODOTTO": "Benzina",
    "PREZZO": "1046.74",
    "IVA": "174.46",
    "ACCISA": "520.32",
    "NETTO": "351.96"
  },
  {
    "ANNO": 2001,
    "CODICE_MESE": 2,
    "NOME_MESE": "Febbraio",
    "CODICE_PRODOTTO": 1,
    "NOME_PRODOTTO": "Benzina",
    "PREZZO": "1048.67",
    "IVA": "174.78",
    "ACCISA": "520.32",
    "NETTO": "353.56"
  },
  {
    "ANNO": 2001,
    "CODICE_MESE": 3,
    "NOME_MESE": "Marzo",
    "CODICE_PRODOTTO": 1,
    "NOME_PRODOTTO": "Benzina",
    "PREZZO": "1051.86",
    "IVA": "175.31",
    "ACCISA": "520.32",
    "NETTO": "356.22"
  },
  {
    "ANNO": 2001,
    "CODICE_MESE": 4,
    "NOME_MESE": "Aprile",
    "CODICE_PRODOTTO": 1,
    "NOME_PRODOTTO": "Benzina",
    "PREZZO": "1070.51",
    "IVA": "178.42",
    "ACCISA": "520.32",
    "NETTO": "371.77"
  },
  {
    "ANNO": 2001,
    "CODICE_MESE": 5,
    "NOME_MESE": "Maggio",
    "CODICE_PRODOTTO": 1,
    "NOME_PRODOTTO": "Benzina",
    "PREZZO": "1111.5",
    "IVA": "185.25",
    "ACCISA": "520.32",
    "NETTO": "405.93"
  },
  {
    "ANNO": 2001,
    "CODICE_MESE": 6,
    "NOME_MESE": "Giugno",
    "CODICE_PRODOTTO": 1,
    "NOME_PRODOTTO": "Benzina",
    "PREZZO": "1110.86",
    "IVA": "185.14",
    "ACCISA": "520.32",
    "NETTO": "405.4"
  },
  {
    "ANNO": 2001,
    "CODICE_MESE": 7,
    "NOME_MESE": "Luglio",
    "CODICE_PRODOTTO": 1,
    "NOME_PRODOTTO": "Benzina",
    "PREZZO": "1064.2",
    "IVA": "177.37",
    "ACCISA": "520.32",
    "NETTO": "366.51"
  },
  {
    "ANNO": 2001,
    "CODICE_MESE": 8,
    "NOME_MESE": "Agosto",
    "CODICE_PRODOTTO": 1,
    "NOME_PRODOTTO": "Benzina",
    "PREZZO": "1042.01",
    "IVA": "173.67",
    "ACCISA": "520.32",
    "NETTO": "348.02"
  },
  {
    "ANNO": 2001,
    "CODICE_MESE": 9,
    "NOME_MESE": "Settembre",
    "CODICE_PRODOTTO": 1,
    "NOME_PRODOTTO": "Benzina",
    "PREZZO": "1050.39",
    "IVA": "175.06",
    "ACCISA": "520.32",
    "NETTO": "355"
  },
  {
    "ANNO": 2001,
    "CODICE_MESE": 10,
    "NOME_MESE": "Ottobre",
    "CODICE_PRODOTTO": 1,
    "NOME_PRODOTTO": "Benzina",
    "PREZZO": "1026.77",
    "IVA": "171.13",
    "ACCISA": "520.32",
    "NETTO": "335.32"
  },
  {
    "ANNO": 2001,
    "CODICE_MESE": 11,
    "NOME_MESE": "Novembre",
    "CODICE_PRODOTTO": 1,
    "NOME_PRODOTTO": "Benzina",
    "PREZZO": "1006.37",
    "IVA": "167.73",
    "ACCISA": "538.97",
    "NETTO": "299.67"
  },
  {
    "ANNO": 2001,
    "CODICE_MESE": 12,
    "NOME_MESE": "Dicembre",
    "CODICE_PRODOTTO": 1,
    "NOME_PRODOTTO": "Benzina",
    "PREZZO": "993.15",
    "IVA": "165.52",
    "ACCISA": "541.84",
    "NETTO": "285.78"
  },
  {
    "ANNO": 2002,
    "CODICE_MESE": 1,
    "NOME_MESE": "Gennaio",
    "CODICE_PRODOTTO": 1,
    "NOME_PRODOTTO": "Benzina",
    "PREZZO": "992.39",
    "IVA": "165.4",
    "ACCISA": "541.83",
    "NETTO": "285.3"
  },
  {
    "ANNO": 2002,
    "CODICE_MESE": 2,
    "NOME_MESE": "Febbraio",
    "CODICE_PRODOTTO": 1,
    "NOME_PRODOTTO": "Benzina",
    "PREZZO": "1000.95",
    "IVA": "166.82",
    "ACCISA": "541.84",
    "NETTO": "292.28"
  },
  {
    "ANNO": 2002,
    "CODICE_MESE": 3,
    "NOME_MESE": "Marzo",
    "CODICE_PRODOTTO": 1,
    "NOME_PRODOTTO": "Benzina",
    "PREZZO": "1023.92",
    "IVA": "170.65",
    "ACCISA": "541.84",
    "NETTO": "311.43"
  },
  {
    "ANNO": 2002,
    "CODICE_MESE": 4,
    "NOME_MESE": "Aprile",
    "CODICE_PRODOTTO": 1,
    "NOME_PRODOTTO": "Benzina",
    "PREZZO": "1063.36",
    "IVA": "177.23",
    "ACCISA": "541.84",
    "NETTO": "344.29"
  },
  {
    "ANNO": 2002,
    "CODICE_MESE": 5,
    "NOME_MESE": "Maggio",
    "CODICE_PRODOTTO": 1,
    "NOME_PRODOTTO": "Benzina",
    "PREZZO": "1071.58",
    "IVA": "178.59",
    "ACCISA": "541.84",
    "NETTO": "351.14"
  },
  {
    "ANNO": 2002,
    "CODICE_MESE": 6,
    "NOME_MESE": "Giugno",
    "CODICE_PRODOTTO": 1,
    "NOME_PRODOTTO": "Benzina",
    "PREZZO": "1061.11",
    "IVA": "176.85",
    "ACCISA": "541.84",
    "NETTO": "342.42"
  },
  {
    "ANNO": 2002,
    "CODICE_MESE": 7,
    "NOME_MESE": "Luglio",
    "CODICE_PRODOTTO": 1,
    "NOME_PRODOTTO": "Benzina",
    "PREZZO": "1052.43",
    "IVA": "175.4",
    "ACCISA": "541.84",
    "NETTO": "335.18"
  },
  {
    "ANNO": 2002,
    "CODICE_MESE": 8,
    "NOME_MESE": "Agosto",
    "CODICE_PRODOTTO": 1,
    "NOME_PRODOTTO": "Benzina",
    "PREZZO": "1052.57",
    "IVA": "175.43",
    "ACCISA": "541.84",
    "NETTO": "335.3"
  },
  {
    "ANNO": 2002,
    "CODICE_MESE": 9,
    "NOME_MESE": "Settembre",
    "CODICE_PRODOTTO": 1,
    "NOME_PRODOTTO": "Benzina",
    "PREZZO": "1061.73",
    "IVA": "176.95",
    "ACCISA": "541.84",
    "NETTO": "342.94"
  },
  {
    "ANNO": 2002,
    "CODICE_MESE": 10,
    "NOME_MESE": "Ottobre",
    "CODICE_PRODOTTO": 1,
    "NOME_PRODOTTO": "Benzina",
    "PREZZO": "1068.08",
    "IVA": "178.01",
    "ACCISA": "541.84",
    "NETTO": "348.23"
  },
  {
    "ANNO": 2002,
    "CODICE_MESE": 11,
    "NOME_MESE": "Novembre",
    "CODICE_PRODOTTO": 1,
    "NOME_PRODOTTO": "Benzina",
    "PREZZO": "1052.98",
    "IVA": "175.5",
    "ACCISA": "541.84",
    "NETTO": "335.64"
  },
  {
    "ANNO": 2002,
    "CODICE_MESE": 12,
    "NOME_MESE": "Dicembre",
    "CODICE_PRODOTTO": 1,
    "NOME_PRODOTTO": "Benzina",
    "PREZZO": "1045.69",
    "IVA": "174.28",
    "ACCISA": "541.84",
    "NETTO": "329.57"
  },
  {
    "ANNO": 2003,
    "CODICE_MESE": 1,
    "NOME_MESE": "Gennaio",
    "CODICE_PRODOTTO": 1,
    "NOME_PRODOTTO": "Benzina",
    "PREZZO": "1068.53",
    "IVA": "178.09",
    "ACCISA": "541.84",
    "NETTO": "348.6"
  },
  {
    "ANNO": 2003,
    "CODICE_MESE": 2,
    "NOME_MESE": "Febbraio",
    "CODICE_PRODOTTO": 1,
    "NOME_PRODOTTO": "Benzina",
    "PREZZO": "1087.79",
    "IVA": "181.3",
    "ACCISA": "541.84",
    "NETTO": "364.65"
  },
  {
    "ANNO": 2003,
    "CODICE_MESE": 3,
    "NOME_MESE": "Marzo",
    "CODICE_PRODOTTO": 1,
    "NOME_PRODOTTO": "Benzina",
    "PREZZO": "1095.02",
    "IVA": "182.5",
    "ACCISA": "541.84",
    "NETTO": "370.68"
  },
  {
    "ANNO": 2003,
    "CODICE_MESE": 4,
    "NOME_MESE": "Aprile",
    "CODICE_PRODOTTO": 1,
    "NOME_PRODOTTO": "Benzina",
    "PREZZO": "1065.23",
    "IVA": "177.54",
    "ACCISA": "541.84",
    "NETTO": "345.86"
  },
  {
    "ANNO": 2003,
    "CODICE_MESE": 5,
    "NOME_MESE": "Maggio",
    "CODICE_PRODOTTO": 1,
    "NOME_PRODOTTO": "Benzina",
    "PREZZO": "1039.79",
    "IVA": "173.3",
    "ACCISA": "541.84",
    "NETTO": "324.65"
  },
  {
    "ANNO": 2003,
    "CODICE_MESE": 6,
    "NOME_MESE": "Giugno",
    "CODICE_PRODOTTO": 1,
    "NOME_PRODOTTO": "Benzina",
    "PREZZO": "1032.03",
    "IVA": "172",
    "ACCISA": "541.84",
    "NETTO": "318.18"
  },
  {
    "ANNO": 2003,
    "CODICE_MESE": 7,
    "NOME_MESE": "Luglio",
    "CODICE_PRODOTTO": 1,
    "NOME_PRODOTTO": "Benzina",
    "PREZZO": "1045.49",
    "IVA": "174.25",
    "ACCISA": "541.84",
    "NETTO": "329.4"
  },
  {
    "ANNO": 2003,
    "CODICE_MESE": 8,
    "NOME_MESE": "Agosto",
    "CODICE_PRODOTTO": 1,
    "NOME_PRODOTTO": "Benzina",
    "PREZZO": "1065.9",
    "IVA": "177.65",
    "ACCISA": "541.84",
    "NETTO": "346.41"
  },
  {
    "ANNO": 2003,
    "CODICE_MESE": 9,
    "NOME_MESE": "Settembre",
    "CODICE_PRODOTTO": 1,
    "NOME_PRODOTTO": "Benzina",
    "PREZZO": "1071.84",
    "IVA": "178.64",
    "ACCISA": "541.84",
    "NETTO": "351.36"
  },
  {
    "ANNO": 2003,
    "CODICE_MESE": 10,
    "NOME_MESE": "Ottobre",
    "CODICE_PRODOTTO": 1,
    "NOME_PRODOTTO": "Benzina",
    "PREZZO": "1043.94",
    "IVA": "173.99",
    "ACCISA": "541.84",
    "NETTO": "328.11"
  },
  {
    "ANNO": 2003,
    "CODICE_MESE": 11,
    "NOME_MESE": "Novembre",
    "CODICE_PRODOTTO": 1,
    "NOME_PRODOTTO": "Benzina",
    "PREZZO": "1043.37",
    "IVA": "173.9",
    "ACCISA": "541.84",
    "NETTO": "327.63"
  },
  {
    "ANNO": 2003,
    "CODICE_MESE": 12,
    "NOME_MESE": "Dicembre",
    "CODICE_PRODOTTO": 1,
    "NOME_PRODOTTO": "Benzina",
    "PREZZO": "1036.82",
    "IVA": "172.8",
    "ACCISA": "541.84",
    "NETTO": "322.18"
  },
  {
    "ANNO": 2004,
    "CODICE_MESE": 1,
    "NOME_MESE": "Gennaio",
    "CODICE_PRODOTTO": 1,
    "NOME_PRODOTTO": "Benzina",
    "PREZZO": "1047.2",
    "IVA": "174.53",
    "ACCISA": "556.47",
    "NETTO": "316.2"
  },
  {
    "ANNO": 2004,
    "CODICE_MESE": 2,
    "NOME_MESE": "Febbraio",
    "CODICE_PRODOTTO": 1,
    "NOME_PRODOTTO": "Benzina",
    "PREZZO": "1063.1",
    "IVA": "177.18",
    "ACCISA": "558.64",
    "NETTO": "327.28"
  },
  {
    "ANNO": 2004,
    "CODICE_MESE": 3,
    "NOME_MESE": "Marzo",
    "CODICE_PRODOTTO": 1,
    "NOME_PRODOTTO": "Benzina",
    "PREZZO": "1082.15",
    "IVA": "180.36",
    "ACCISA": "558.64",
    "NETTO": "343.15"
  },
  {
    "ANNO": 2004,
    "CODICE_MESE": 4,
    "NOME_MESE": "Aprile",
    "CODICE_PRODOTTO": 1,
    "NOME_PRODOTTO": "Benzina",
    "PREZZO": "1096.99",
    "IVA": "182.83",
    "ACCISA": "558.64",
    "NETTO": "355.52"
  },
  {
    "ANNO": 2004,
    "CODICE_MESE": 5,
    "NOME_MESE": "Maggio",
    "CODICE_PRODOTTO": 1,
    "NOME_PRODOTTO": "Benzina",
    "PREZZO": "1131.29",
    "IVA": "188.55",
    "ACCISA": "558.64",
    "NETTO": "384.1"
  },
  {
    "ANNO": 2004,
    "CODICE_MESE": 6,
    "NOME_MESE": "Giugno",
    "CODICE_PRODOTTO": 1,
    "NOME_PRODOTTO": "Benzina",
    "PREZZO": "1148.14",
    "IVA": "191.35",
    "ACCISA": "558.64",
    "NETTO": "398.15"
  },
  {
    "ANNO": 2004,
    "CODICE_MESE": 7,
    "NOME_MESE": "Luglio",
    "CODICE_PRODOTTO": 1,
    "NOME_PRODOTTO": "Benzina",
    "PREZZO": "1146.85",
    "IVA": "191.14",
    "ACCISA": "558.64",
    "NETTO": "397.07"
  },
  {
    "ANNO": 2004,
    "CODICE_MESE": 8,
    "NOME_MESE": "Agosto",
    "CODICE_PRODOTTO": 1,
    "NOME_PRODOTTO": "Benzina",
    "PREZZO": "1156.74",
    "IVA": "192.79",
    "ACCISA": "558.64",
    "NETTO": "405.31"
  },
  {
    "ANNO": 2004,
    "CODICE_MESE": 9,
    "NOME_MESE": "Settembre",
    "CODICE_PRODOTTO": 1,
    "NOME_PRODOTTO": "Benzina",
    "PREZZO": "1155.81",
    "IVA": "192.64",
    "ACCISA": "558.64",
    "NETTO": "404.53"
  },
  {
    "ANNO": 2004,
    "CODICE_MESE": 10,
    "NOME_MESE": "Ottobre",
    "CODICE_PRODOTTO": 1,
    "NOME_PRODOTTO": "Benzina",
    "PREZZO": "1168.69",
    "IVA": "194.78",
    "ACCISA": "558.64",
    "NETTO": "415.27"
  },
  {
    "ANNO": 2004,
    "CODICE_MESE": 11,
    "NOME_MESE": "Novembre",
    "CODICE_PRODOTTO": 1,
    "NOME_PRODOTTO": "Benzina",
    "PREZZO": "1168.11",
    "IVA": "194.69",
    "ACCISA": "558.64",
    "NETTO": "414.78"
  },
  {
    "ANNO": 2004,
    "CODICE_MESE": 12,
    "NOME_MESE": "Dicembre",
    "CODICE_PRODOTTO": 1,
    "NOME_PRODOTTO": "Benzina",
    "PREZZO": "1132.57",
    "IVA": "188.76",
    "ACCISA": "558.64",
    "NETTO": "385.17"
  },
  {
    "ANNO": 2005,
    "CODICE_MESE": 1,
    "NOME_MESE": "Gennaio",
    "CODICE_PRODOTTO": 1,
    "NOME_PRODOTTO": "Benzina",
    "PREZZO": "1098.07",
    "IVA": "183.01",
    "ACCISA": "558.64",
    "NETTO": "356.41"
  },
  {
    "ANNO": 2005,
    "CODICE_MESE": 2,
    "NOME_MESE": "Febbraio",
    "CODICE_PRODOTTO": 1,
    "NOME_PRODOTTO": "Benzina",
    "PREZZO": "1135.12",
    "IVA": "189.18",
    "ACCISA": "558.83",
    "NETTO": "387.1"
  },
  {
    "ANNO": 2005,
    "CODICE_MESE": 3,
    "NOME_MESE": "Marzo",
    "CODICE_PRODOTTO": 1,
    "NOME_PRODOTTO": "Benzina",
    "PREZZO": "1170.15",
    "IVA": "195.02",
    "ACCISA": "564",
    "NETTO": "411.13"
  },
  {
    "ANNO": 2005,
    "CODICE_MESE": 4,
    "NOME_MESE": "Aprile",
    "CODICE_PRODOTTO": 1,
    "NOME_PRODOTTO": "Benzina",
    "PREZZO": "1219.72",
    "IVA": "203.29",
    "ACCISA": "564",
    "NETTO": "452.43"
  },
  {
    "ANNO": 2005,
    "CODICE_MESE": 5,
    "NOME_MESE": "Maggio",
    "CODICE_PRODOTTO": 1,
    "NOME_PRODOTTO": "Benzina",
    "PREZZO": "1208.74",
    "IVA": "201.46",
    "ACCISA": "564",
    "NETTO": "443.29"
  },
  {
    "ANNO": 2005,
    "CODICE_MESE": 6,
    "NOME_MESE": "Giugno",
    "CODICE_PRODOTTO": 1,
    "NOME_PRODOTTO": "Benzina",
    "PREZZO": "1209",
    "IVA": "201.5",
    "ACCISA": "564",
    "NETTO": "443.5"
  },
  {
    "ANNO": 2005,
    "CODICE_MESE": 7,
    "NOME_MESE": "Luglio",
    "CODICE_PRODOTTO": 1,
    "NOME_PRODOTTO": "Benzina",
    "PREZZO": "1244.86",
    "IVA": "207.48",
    "ACCISA": "564",
    "NETTO": "473.38"
  },
  {
    "ANNO": 2005,
    "CODICE_MESE": 8,
    "NOME_MESE": "Agosto",
    "CODICE_PRODOTTO": 1,
    "NOME_PRODOTTO": "Benzina",
    "PREZZO": "1255.86",
    "IVA": "209.31",
    "ACCISA": "564",
    "NETTO": "482.55"
  },
  {
    "ANNO": 2005,
    "CODICE_MESE": 9,
    "NOME_MESE": "Settembre",
    "CODICE_PRODOTTO": 1,
    "NOME_PRODOTTO": "Benzina",
    "PREZZO": "1303.59",
    "IVA": "217.26",
    "ACCISA": "564",
    "NETTO": "522.32"
  },
  {
    "ANNO": 2005,
    "CODICE_MESE": 10,
    "NOME_MESE": "Ottobre",
    "CODICE_PRODOTTO": 1,
    "NOME_PRODOTTO": "Benzina",
    "PREZZO": "1321.38",
    "IVA": "220.23",
    "ACCISA": "564",
    "NETTO": "537.15"
  },
  {
    "ANNO": 2005,
    "CODICE_MESE": 11,
    "NOME_MESE": "Novembre",
    "CODICE_PRODOTTO": 1,
    "NOME_PRODOTTO": "Benzina",
    "PREZZO": "1243.77",
    "IVA": "207.3",
    "ACCISA": "564",
    "NETTO": "472.47"
  },
  {
    "ANNO": 2005,
    "CODICE_MESE": 12,
    "NOME_MESE": "Dicembre",
    "CODICE_PRODOTTO": 1,
    "NOME_PRODOTTO": "Benzina",
    "PREZZO": "1220.03",
    "IVA": "203.34",
    "ACCISA": "564",
    "NETTO": "452.7"
  },
  {
    "ANNO": 2006,
    "CODICE_MESE": 1,
    "NOME_MESE": "Gennaio",
    "CODICE_PRODOTTO": 1,
    "NOME_PRODOTTO": "Benzina",
    "PREZZO": "1248.31",
    "IVA": "208.05",
    "ACCISA": "564",
    "NETTO": "476.26"
  },
  {
    "ANNO": 2006,
    "CODICE_MESE": 2,
    "NOME_MESE": "Febbraio",
    "CODICE_PRODOTTO": 1,
    "NOME_PRODOTTO": "Benzina",
    "PREZZO": "1248.77",
    "IVA": "208.13",
    "ACCISA": "564",
    "NETTO": "476.64"
  },
  {
    "ANNO": 2006,
    "CODICE_MESE": 3,
    "NOME_MESE": "Marzo",
    "CODICE_PRODOTTO": 1,
    "NOME_PRODOTTO": "Benzina",
    "PREZZO": "1253.42",
    "IVA": "208.91",
    "ACCISA": "564",
    "NETTO": "480.51"
  },
  {
    "ANNO": 2006,
    "CODICE_MESE": 4,
    "NOME_MESE": "Aprile",
    "CODICE_PRODOTTO": 1,
    "NOME_PRODOTTO": "Benzina",
    "PREZZO": "1298.51",
    "IVA": "216.42",
    "ACCISA": "564",
    "NETTO": "518.09"
  },
  {
    "ANNO": 2006,
    "CODICE_MESE": 5,
    "NOME_MESE": "Maggio",
    "CODICE_PRODOTTO": 1,
    "NOME_PRODOTTO": "Benzina",
    "PREZZO": "1341.37",
    "IVA": "223.56",
    "ACCISA": "564",
    "NETTO": "553.81"
  },
  {
    "ANNO": 2006,
    "CODICE_MESE": 6,
    "NOME_MESE": "Giugno",
    "CODICE_PRODOTTO": 1,
    "NOME_PRODOTTO": "Benzina",
    "PREZZO": "1336.52",
    "IVA": "222.75",
    "ACCISA": "564",
    "NETTO": "549.77"
  },
  {
    "ANNO": 2006,
    "CODICE_MESE": 7,
    "NOME_MESE": "Luglio",
    "CODICE_PRODOTTO": 1,
    "NOME_PRODOTTO": "Benzina",
    "PREZZO": "1371.5",
    "IVA": "228.58",
    "ACCISA": "564",
    "NETTO": "578.92"
  },
  {
    "ANNO": 2006,
    "CODICE_MESE": 8,
    "NOME_MESE": "Agosto",
    "CODICE_PRODOTTO": 1,
    "NOME_PRODOTTO": "Benzina",
    "PREZZO": "1374.96",
    "IVA": "229.16",
    "ACCISA": "564",
    "NETTO": "581.8"
  },
  {
    "ANNO": 2006,
    "CODICE_MESE": 9,
    "NOME_MESE": "Settembre",
    "CODICE_PRODOTTO": 1,
    "NOME_PRODOTTO": "Benzina",
    "PREZZO": "1269.75",
    "IVA": "211.62",
    "ACCISA": "564",
    "NETTO": "494.13"
  },
  {
    "ANNO": 2006,
    "CODICE_MESE": 10,
    "NOME_MESE": "Ottobre",
    "CODICE_PRODOTTO": 1,
    "NOME_PRODOTTO": "Benzina",
    "PREZZO": "1222.56",
    "IVA": "203.76",
    "ACCISA": "564",
    "NETTO": "454.8"
  },
  {
    "ANNO": 2006,
    "CODICE_MESE": 11,
    "NOME_MESE": "Novembre",
    "CODICE_PRODOTTO": 1,
    "NOME_PRODOTTO": "Benzina",
    "PREZZO": "1219.52",
    "IVA": "203.25",
    "ACCISA": "564",
    "NETTO": "452.27"
  },
  {
    "ANNO": 2006,
    "CODICE_MESE": 12,
    "NOME_MESE": "Dicembre",
    "CODICE_PRODOTTO": 1,
    "NOME_PRODOTTO": "Benzina",
    "PREZZO": "1219.19",
    "IVA": "203.2",
    "ACCISA": "564",
    "NETTO": "451.99"
  },
  {
    "ANNO": 2007,
    "CODICE_MESE": 1,
    "NOME_MESE": "Gennaio",
    "CODICE_PRODOTTO": 1,
    "NOME_PRODOTTO": "Benzina",
    "PREZZO": "1209.85",
    "IVA": "201.64",
    "ACCISA": "564",
    "NETTO": "444.21"
  },
  {
    "ANNO": 2007,
    "CODICE_MESE": 2,
    "NOME_MESE": "Febbraio",
    "CODICE_PRODOTTO": 1,
    "NOME_PRODOTTO": "Benzina",
    "PREZZO": "1202.28",
    "IVA": "200.38",
    "ACCISA": "564",
    "NETTO": "437.9"
  },
  {
    "ANNO": 2007,
    "CODICE_MESE": 3,
    "NOME_MESE": "Marzo",
    "CODICE_PRODOTTO": 1,
    "NOME_PRODOTTO": "Benzina",
    "PREZZO": "1236.25",
    "IVA": "206.04",
    "ACCISA": "564",
    "NETTO": "466.21"
  },
  {
    "ANNO": 2007,
    "CODICE_MESE": 4,
    "NOME_MESE": "Aprile",
    "CODICE_PRODOTTO": 1,
    "NOME_PRODOTTO": "Benzina",
    "PREZZO": "1267.15",
    "IVA": "211.19",
    "ACCISA": "564",
    "NETTO": "491.96"
  },
  {
    "ANNO": 2007,
    "CODICE_MESE": 5,
    "NOME_MESE": "Maggio",
    "CODICE_PRODOTTO": 1,
    "NOME_PRODOTTO": "Benzina",
    "PREZZO": "1315.3",
    "IVA": "219.22",
    "ACCISA": "564",
    "NETTO": "532.09"
  },
  {
    "ANNO": 2007,
    "CODICE_MESE": 6,
    "NOME_MESE": "Giugno",
    "CODICE_PRODOTTO": 1,
    "NOME_PRODOTTO": "Benzina",
    "PREZZO": "1346.24",
    "IVA": "224.38",
    "ACCISA": "564",
    "NETTO": "557.86"
  },
  {
    "ANNO": 2007,
    "CODICE_MESE": 7,
    "NOME_MESE": "Luglio",
    "CODICE_PRODOTTO": 1,
    "NOME_PRODOTTO": "Benzina",
    "PREZZO": "1354.23",
    "IVA": "225.71",
    "ACCISA": "564",
    "NETTO": "564.52"
  },
  {
    "ANNO": 2007,
    "CODICE_MESE": 8,
    "NOME_MESE": "Agosto",
    "CODICE_PRODOTTO": 1,
    "NOME_PRODOTTO": "Benzina",
    "PREZZO": "1315.04",
    "IVA": "219.17",
    "ACCISA": "564",
    "NETTO": "531.86"
  },
  {
    "ANNO": 2007,
    "CODICE_MESE": 9,
    "NOME_MESE": "Settembre",
    "CODICE_PRODOTTO": 1,
    "NOME_PRODOTTO": "Benzina",
    "PREZZO": "1306",
    "IVA": "217.67",
    "ACCISA": "564",
    "NETTO": "524.33"
  },
  {
    "ANNO": 2007,
    "CODICE_MESE": 10,
    "NOME_MESE": "Ottobre",
    "CODICE_PRODOTTO": 1,
    "NOME_PRODOTTO": "Benzina",
    "PREZZO": "1313.33",
    "IVA": "218.89",
    "ACCISA": "564",
    "NETTO": "530.44"
  },
  {
    "ANNO": 2007,
    "CODICE_MESE": 11,
    "NOME_MESE": "Novembre",
    "CODICE_PRODOTTO": 1,
    "NOME_PRODOTTO": "Benzina",
    "PREZZO": "1347.84",
    "IVA": "224.64",
    "ACCISA": "564",
    "NETTO": "559.2"
  },
  {
    "ANNO": 2007,
    "CODICE_MESE": 12,
    "NOME_MESE": "Dicembre",
    "CODICE_PRODOTTO": 1,
    "NOME_PRODOTTO": "Benzina",
    "PREZZO": "1360.84",
    "IVA": "226.81",
    "ACCISA": "564",
    "NETTO": "570.04"
  },
  {
    "ANNO": 2008,
    "CODICE_MESE": 1,
    "NOME_MESE": "Gennaio",
    "CODICE_PRODOTTO": 1,
    "NOME_PRODOTTO": "Benzina",
    "PREZZO": "1364.44",
    "IVA": "227.41",
    "ACCISA": "564",
    "NETTO": "573.03"
  },
  {
    "ANNO": 2008,
    "CODICE_MESE": 2,
    "NOME_MESE": "Febbraio",
    "CODICE_PRODOTTO": 1,
    "NOME_PRODOTTO": "Benzina",
    "PREZZO": "1361.6",
    "IVA": "226.93",
    "ACCISA": "564",
    "NETTO": "570.67"
  },
  {
    "ANNO": 2008,
    "CODICE_MESE": 3,
    "NOME_MESE": "Marzo",
    "CODICE_PRODOTTO": 1,
    "NOME_PRODOTTO": "Benzina",
    "PREZZO": "1386.16",
    "IVA": "231.03",
    "ACCISA": "563.46",
    "NETTO": "591.68"
  },
  {
    "ANNO": 2008,
    "CODICE_MESE": 4,
    "NOME_MESE": "Aprile",
    "CODICE_PRODOTTO": 1,
    "NOME_PRODOTTO": "Benzina",
    "PREZZO": "1374.79",
    "IVA": "229.13",
    "ACCISA": "547.17",
    "NETTO": "598.48"
  },
  {
    "ANNO": 2008,
    "CODICE_MESE": 5,
    "NOME_MESE": "Maggio",
    "CODICE_PRODOTTO": 1,
    "NOME_PRODOTTO": "Benzina",
    "PREZZO": "1455.25",
    "IVA": "242.54",
    "ACCISA": "561.83",
    "NETTO": "650.88"
  },
  {
    "ANNO": 2008,
    "CODICE_MESE": 6,
    "NOME_MESE": "Giugno",
    "CODICE_PRODOTTO": 1,
    "NOME_PRODOTTO": "Benzina",
    "PREZZO": "1512.13",
    "IVA": "252.02",
    "ACCISA": "564",
    "NETTO": "696.11"
  },
  {
    "ANNO": 2008,
    "CODICE_MESE": 7,
    "NOME_MESE": "Luglio",
    "CODICE_PRODOTTO": 1,
    "NOME_PRODOTTO": "Benzina",
    "PREZZO": "1522.64",
    "IVA": "253.77",
    "ACCISA": "564",
    "NETTO": "704.87"
  },
  {
    "ANNO": 2008,
    "CODICE_MESE": 8,
    "NOME_MESE": "Agosto",
    "CODICE_PRODOTTO": 1,
    "NOME_PRODOTTO": "Benzina",
    "PREZZO": "1458.25",
    "IVA": "243.04",
    "ACCISA": "564",
    "NETTO": "651.21"
  },
  {
    "ANNO": 2008,
    "CODICE_MESE": 9,
    "NOME_MESE": "Settembre",
    "CODICE_PRODOTTO": 1,
    "NOME_PRODOTTO": "Benzina",
    "PREZZO": "1435.85",
    "IVA": "239.31",
    "ACCISA": "564",
    "NETTO": "632.54"
  },
  {
    "ANNO": 2008,
    "CODICE_MESE": 10,
    "NOME_MESE": "Ottobre",
    "CODICE_PRODOTTO": 1,
    "NOME_PRODOTTO": "Benzina",
    "PREZZO": "1346.35",
    "IVA": "224.39",
    "ACCISA": "564",
    "NETTO": "557.96"
  },
  {
    "ANNO": 2008,
    "CODICE_MESE": 11,
    "NOME_MESE": "Novembre",
    "CODICE_PRODOTTO": 1,
    "NOME_PRODOTTO": "Benzina",
    "PREZZO": "1211.92",
    "IVA": "201.99",
    "ACCISA": "564",
    "NETTO": "445.93"
  },
  {
    "ANNO": 2008,
    "CODICE_MESE": 12,
    "NOME_MESE": "Dicembre",
    "CODICE_PRODOTTO": 1,
    "NOME_PRODOTTO": "Benzina",
    "PREZZO": "1120.88",
    "IVA": "186.81",
    "ACCISA": "564",
    "NETTO": "370.07"
  },
  {
    "ANNO": 2009,
    "CODICE_MESE": 1,
    "NOME_MESE": "Gennaio",
    "CODICE_PRODOTTO": 1,
    "NOME_PRODOTTO": "Benzina",
    "PREZZO": "1113.64",
    "IVA": "185.6",
    "ACCISA": "564",
    "NETTO": "364.03"
  },
  {
    "ANNO": 2009,
    "CODICE_MESE": 2,
    "NOME_MESE": "Febbraio",
    "CODICE_PRODOTTO": 1,
    "NOME_PRODOTTO": "Benzina",
    "PREZZO": "1140.8",
    "IVA": "190.13",
    "ACCISA": "564",
    "NETTO": "386.67"
  },
  {
    "ANNO": 2009,
    "CODICE_MESE": 3,
    "NOME_MESE": "Marzo",
    "CODICE_PRODOTTO": 1,
    "NOME_PRODOTTO": "Benzina",
    "PREZZO": "1162.61",
    "IVA": "193.77",
    "ACCISA": "564",
    "NETTO": "404.84"
  },
  {
    "ANNO": 2009,
    "CODICE_MESE": 4,
    "NOME_MESE": "Aprile",
    "CODICE_PRODOTTO": 1,
    "NOME_PRODOTTO": "Benzina",
    "PREZZO": "1185.29",
    "IVA": "197.55",
    "ACCISA": "564",
    "NETTO": "423.74"
  },
  {
    "ANNO": 2009,
    "CODICE_MESE": 5,
    "NOME_MESE": "Maggio",
    "CODICE_PRODOTTO": 1,
    "NOME_PRODOTTO": "Benzina",
    "PREZZO": "1224.56",
    "IVA": "204.09",
    "ACCISA": "564",
    "NETTO": "456.47"
  },
  {
    "ANNO": 2009,
    "CODICE_MESE": 6,
    "NOME_MESE": "Giugno",
    "CODICE_PRODOTTO": 1,
    "NOME_PRODOTTO": "Benzina",
    "PREZZO": "1294.84",
    "IVA": "215.8",
    "ACCISA": "564",
    "NETTO": "515.03"
  },
  {
    "ANNO": 2009,
    "CODICE_MESE": 7,
    "NOME_MESE": "Luglio",
    "CODICE_PRODOTTO": 1,
    "NOME_PRODOTTO": "Benzina",
    "PREZZO": "1270.52",
    "IVA": "211.75",
    "ACCISA": "564",
    "NETTO": "494.77"
  },
  {
    "ANNO": 2009,
    "CODICE_MESE": 8,
    "NOME_MESE": "Agosto",
    "CODICE_PRODOTTO": 1,
    "NOME_PRODOTTO": "Benzina",
    "PREZZO": "1295.63",
    "IVA": "215.94",
    "ACCISA": "564",
    "NETTO": "515.69"
  },
  {
    "ANNO": 2009,
    "CODICE_MESE": 9,
    "NOME_MESE": "Settembre",
    "CODICE_PRODOTTO": 1,
    "NOME_PRODOTTO": "Benzina",
    "PREZZO": "1271.35",
    "IVA": "211.89",
    "ACCISA": "564",
    "NETTO": "495.46"
  },
  {
    "ANNO": 2009,
    "CODICE_MESE": 10,
    "NOME_MESE": "Ottobre",
    "CODICE_PRODOTTO": 1,
    "NOME_PRODOTTO": "Benzina",
    "PREZZO": "1256.37",
    "IVA": "209.39",
    "ACCISA": "564",
    "NETTO": "482.98"
  },
  {
    "ANNO": 2009,
    "CODICE_MESE": 11,
    "NOME_MESE": "Novembre",
    "CODICE_PRODOTTO": 1,
    "NOME_PRODOTTO": "Benzina",
    "PREZZO": "1289.44",
    "IVA": "214.9",
    "ACCISA": "564",
    "NETTO": "510.54"
  },
  {
    "ANNO": 2009,
    "CODICE_MESE": 12,
    "NOME_MESE": "Dicembre",
    "CODICE_PRODOTTO": 1,
    "NOME_PRODOTTO": "Benzina",
    "PREZZO": "1273.66",
    "IVA": "212.28",
    "ACCISA": "564",
    "NETTO": "497.38"
  },
  {
    "ANNO": 2010,
    "CODICE_MESE": 1,
    "NOME_MESE": "Gennaio",
    "CODICE_PRODOTTO": 1,
    "NOME_PRODOTTO": "Benzina",
    "PREZZO": "1305.08",
    "IVA": "217.51",
    "ACCISA": "564",
    "NETTO": "523.57"
  },
  {
    "ANNO": 2010,
    "CODICE_MESE": 2,
    "NOME_MESE": "Febbraio",
    "CODICE_PRODOTTO": 1,
    "NOME_PRODOTTO": "Benzina",
    "PREZZO": "1312.88",
    "IVA": "218.82",
    "ACCISA": "564",
    "NETTO": "530.06"
  },
  {
    "ANNO": 2010,
    "CODICE_MESE": 3,
    "NOME_MESE": "Marzo",
    "CODICE_PRODOTTO": 1,
    "NOME_PRODOTTO": "Benzina",
    "PREZZO": "1358.36",
    "IVA": "226.39",
    "ACCISA": "564",
    "NETTO": "567.97"
  },
  {
    "ANNO": 2010,
    "CODICE_MESE": 4,
    "NOME_MESE": "Aprile",
    "CODICE_PRODOTTO": 1,
    "NOME_PRODOTTO": "Benzina",
    "PREZZO": "1386.46",
    "IVA": "231.08",
    "ACCISA": "564",
    "NETTO": "591.39"
  },
  {
    "ANNO": 2010,
    "CODICE_MESE": 5,
    "NOME_MESE": "Maggio",
    "CODICE_PRODOTTO": 1,
    "NOME_PRODOTTO": "Benzina",
    "PREZZO": "1391.58",
    "IVA": "231.93",
    "ACCISA": "564",
    "NETTO": "595.65"
  },
  {
    "ANNO": 2010,
    "CODICE_MESE": 6,
    "NOME_MESE": "Giugno",
    "CODICE_PRODOTTO": 1,
    "NOME_PRODOTTO": "Benzina",
    "PREZZO": "1377.42",
    "IVA": "229.57",
    "ACCISA": "564",
    "NETTO": "583.85"
  },
  {
    "ANNO": 2010,
    "CODICE_MESE": 7,
    "NOME_MESE": "Luglio",
    "CODICE_PRODOTTO": 1,
    "NOME_PRODOTTO": "Benzina",
    "PREZZO": "1371.76",
    "IVA": "228.63",
    "ACCISA": "564",
    "NETTO": "579.13"
  },
  {
    "ANNO": 2010,
    "CODICE_MESE": 8,
    "NOME_MESE": "Agosto",
    "CODICE_PRODOTTO": 1,
    "NOME_PRODOTTO": "Benzina",
    "PREZZO": "1362.67",
    "IVA": "227.11",
    "ACCISA": "564",
    "NETTO": "571.55"
  },
  {
    "ANNO": 2010,
    "CODICE_MESE": 9,
    "NOME_MESE": "Settembre",
    "CODICE_PRODOTTO": 1,
    "NOME_PRODOTTO": "Benzina",
    "PREZZO": "1355.34",
    "IVA": "225.89",
    "ACCISA": "564",
    "NETTO": "565.45"
  },
  {
    "ANNO": 2010,
    "CODICE_MESE": 10,
    "NOME_MESE": "Ottobre",
    "CODICE_PRODOTTO": 1,
    "NOME_PRODOTTO": "Benzina",
    "PREZZO": "1351.82",
    "IVA": "225.3",
    "ACCISA": "564",
    "NETTO": "562.52"
  },
  {
    "ANNO": 2010,
    "CODICE_MESE": 11,
    "NOME_MESE": "Novembre",
    "CODICE_PRODOTTO": 1,
    "NOME_PRODOTTO": "Benzina",
    "PREZZO": "1369.93",
    "IVA": "228.32",
    "ACCISA": "564",
    "NETTO": "577.61"
  },
  {
    "ANNO": 2010,
    "CODICE_MESE": 12,
    "NOME_MESE": "Dicembre",
    "CODICE_PRODOTTO": 1,
    "NOME_PRODOTTO": "Benzina",
    "PREZZO": "1411.52",
    "IVA": "235.25",
    "ACCISA": "564",
    "NETTO": "612.26"
  },
  {
    "ANNO": 2011,
    "CODICE_MESE": 1,
    "NOME_MESE": "Gennaio",
    "CODICE_PRODOTTO": 1,
    "NOME_PRODOTTO": "Benzina",
    "PREZZO": "1452.56",
    "IVA": "242.09",
    "ACCISA": "564",
    "NETTO": "646.47"
  },
  {
    "ANNO": 2011,
    "CODICE_MESE": 2,
    "NOME_MESE": "Febbraio",
    "CODICE_PRODOTTO": 1,
    "NOME_PRODOTTO": "Benzina",
    "PREZZO": "1469.63",
    "IVA": "244.94",
    "ACCISA": "564",
    "NETTO": "660.69"
  },
  {
    "ANNO": 2011,
    "CODICE_MESE": 3,
    "NOME_MESE": "Marzo",
    "CODICE_PRODOTTO": 1,
    "NOME_PRODOTTO": "Benzina",
    "PREZZO": "1523.15",
    "IVA": "253.86",
    "ACCISA": "564",
    "NETTO": "705.3"
  },
  {
    "ANNO": 2011,
    "CODICE_MESE": 4,
    "NOME_MESE": "Aprile",
    "CODICE_PRODOTTO": 1,
    "NOME_PRODOTTO": "Benzina",
    "PREZZO": "1542.19",
    "IVA": "257.03",
    "ACCISA": "568.87",
    "NETTO": "716.3"
  },
  {
    "ANNO": 2011,
    "CODICE_MESE": 5,
    "NOME_MESE": "Maggio",
    "CODICE_PRODOTTO": 1,
    "NOME_PRODOTTO": "Benzina",
    "PREZZO": "1548.69",
    "IVA": "258.12",
    "ACCISA": "571.3",
    "NETTO": "719.28"
  },
  {
    "ANNO": 2011,
    "CODICE_MESE": 6,
    "NOME_MESE": "Giugno",
    "CODICE_PRODOTTO": 1,
    "NOME_PRODOTTO": "Benzina",
    "PREZZO": "1529.36",
    "IVA": "254.89",
    "ACCISA": "571.3",
    "NETTO": "703.17"
  },
  {
    "ANNO": 2011,
    "CODICE_MESE": 7,
    "NOME_MESE": "Luglio",
    "CODICE_PRODOTTO": 1,
    "NOME_PRODOTTO": "Benzina",
    "PREZZO": "1576.16",
    "IVA": "262.69",
    "ACCISA": "613.2",
    "NETTO": "700.27"
  },
  {
    "ANNO": 2011,
    "CODICE_MESE": 8,
    "NOME_MESE": "Agosto",
    "CODICE_PRODOTTO": 1,
    "NOME_PRODOTTO": "Benzina",
    "PREZZO": "1586.02",
    "IVA": "264.34",
    "ACCISA": "613.2",
    "NETTO": "708.48"
  },
  {
    "ANNO": 2011,
    "CODICE_MESE": 9,
    "NOME_MESE": "Settembre",
    "CODICE_PRODOTTO": 1,
    "NOME_PRODOTTO": "Benzina",
    "PREZZO": "1589.69",
    "IVA": "269.37",
    "ACCISA": "613.2",
    "NETTO": "707.12"
  },
  {
    "ANNO": 2011,
    "CODICE_MESE": 10,
    "NOME_MESE": "Ottobre",
    "CODICE_PRODOTTO": 1,
    "NOME_PRODOTTO": "Benzina",
    "PREZZO": "1592.27",
    "IVA": "276.35",
    "ACCISA": "613.2",
    "NETTO": "702.73"
  },
  {
    "ANNO": 2011,
    "CODICE_MESE": 11,
    "NOME_MESE": "Novembre",
    "CODICE_PRODOTTO": 1,
    "NOME_PRODOTTO": "Benzina",
    "PREZZO": "1591.67",
    "IVA": "276.24",
    "ACCISA": "622.1",
    "NETTO": "693.33"
  },
  {
    "ANNO": 2011,
    "CODICE_MESE": 12,
    "NOME_MESE": "Dicembre",
    "CODICE_PRODOTTO": 1,
    "NOME_PRODOTTO": "Benzina",
    "PREZZO": "1655.16",
    "IVA": "287.26",
    "ACCISA": "688.31",
    "NETTO": "679.59"
  },
  {
    "ANNO": 2012,
    "CODICE_MESE": 1,
    "NOME_MESE": "Gennaio",
    "CODICE_PRODOTTO": 1,
    "NOME_PRODOTTO": "Benzina",
    "PREZZO": "1700.9",
    "IVA": "295.2",
    "ACCISA": "704.2",
    "NETTO": "701.5"
  },
  {
    "ANNO": 2012,
    "CODICE_MESE": 2,
    "NOME_MESE": "Febbraio",
    "CODICE_PRODOTTO": 1,
    "NOME_PRODOTTO": "Benzina",
    "PREZZO": "1737.8",
    "IVA": "301.6",
    "ACCISA": "704.2",
    "NETTO": "732"
  },
  {
    "ANNO": 2012,
    "CODICE_MESE": 3,
    "NOME_MESE": "Marzo",
    "CODICE_PRODOTTO": 1,
    "NOME_PRODOTTO": "Benzina",
    "PREZZO": "1799.67",
    "IVA": "312.34",
    "ACCISA": "704.2",
    "NETTO": "783.13"
  },
  {
    "ANNO": 2012,
    "CODICE_MESE": 4,
    "NOME_MESE": "Aprile",
    "CODICE_PRODOTTO": 1,
    "NOME_PRODOTTO": "Benzina",
    "PREZZO": "1850.22",
    "IVA": "321.11",
    "ACCISA": "704.2",
    "NETTO": "824.9"
  },
  {
    "ANNO": 2012,
    "CODICE_MESE": 5,
    "NOME_MESE": "Maggio",
    "CODICE_PRODOTTO": 1,
    "NOME_PRODOTTO": "Benzina",
    "PREZZO": "1805.77",
    "IVA": "313.4",
    "ACCISA": "704.2",
    "NETTO": "788.17"
  },
  {
    "ANNO": 2012,
    "CODICE_MESE": 6,
    "NOME_MESE": "Giugno",
    "CODICE_PRODOTTO": 1,
    "NOME_PRODOTTO": "Benzina",
    "PREZZO": "1760.7",
    "IVA": "305.58",
    "ACCISA": "717.53",
    "NETTO": "737.59"
  },
  {
    "ANNO": 2012,
    "CODICE_MESE": 7,
    "NOME_MESE": "Luglio",
    "CODICE_PRODOTTO": 1,
    "NOME_PRODOTTO": "Benzina",
    "PREZZO": "1750.95",
    "IVA": "303.88",
    "ACCISA": "724.2",
    "NETTO": "722.87"
  },
  {
    "ANNO": 2012,
    "CODICE_MESE": 8,
    "NOME_MESE": "Agosto",
    "CODICE_PRODOTTO": 1,
    "NOME_PRODOTTO": "Benzina",
    "PREZZO": "1818.26",
    "IVA": "315.56",
    "ACCISA": "725.83",
    "NETTO": "776.87"
  },
  {
    "ANNO": 2012,
    "CODICE_MESE": 9,
    "NOME_MESE": "Settembre",
    "CODICE_PRODOTTO": 1,
    "NOME_PRODOTTO": "Benzina",
    "PREZZO": "1870.89",
    "IVA": "324.7",
    "ACCISA": "728.4",
    "NETTO": "817.79"
  },
  {
    "ANNO": 2012,
    "CODICE_MESE": 10,
    "NOME_MESE": "Ottobre",
    "CODICE_PRODOTTO": 1,
    "NOME_PRODOTTO": "Benzina",
    "PREZZO": "1833.91",
    "IVA": "318.28",
    "ACCISA": "728.4",
    "NETTO": "787.23"
  },
  {
    "ANNO": 2012,
    "CODICE_MESE": 11,
    "NOME_MESE": "Novembre",
    "CODICE_PRODOTTO": 1,
    "NOME_PRODOTTO": "Benzina",
    "PREZZO": "1759.07",
    "IVA": "305.3",
    "ACCISA": "728.4",
    "NETTO": "725.37"
  },
  {
    "ANNO": 2012,
    "CODICE_MESE": 12,
    "NOME_MESE": "Dicembre",
    "CODICE_PRODOTTO": 1,
    "NOME_PRODOTTO": "Benzina",
    "PREZZO": "1746.45",
    "IVA": "303.1",
    "ACCISA": "728.4",
    "NETTO": "714.95"
  },
  {
    "ANNO": 2013,
    "CODICE_MESE": 1,
    "NOME_MESE": "Gennaio",
    "CODICE_PRODOTTO": 1,
    "NOME_PRODOTTO": "Benzina",
    "PREZZO": "1749.94",
    "IVA": "303.71",
    "ACCISA": "728.4",
    "NETTO": "717.83"
  },
  {
    "ANNO": 2013,
    "CODICE_MESE": 2,
    "NOME_MESE": "Febbraio",
    "CODICE_PRODOTTO": 1,
    "NOME_PRODOTTO": "Benzina",
    "PREZZO": "1781",
    "IVA": "309.1",
    "ACCISA": "728.4",
    "NETTO": "743.5"
  },
  {
    "ANNO": 2013,
    "CODICE_MESE": 3,
    "NOME_MESE": "Marzo",
    "CODICE_PRODOTTO": 1,
    "NOME_PRODOTTO": "Benzina",
    "PREZZO": "1796.91",
    "IVA": "311.86",
    "ACCISA": "728.4",
    "NETTO": "756.65"
  },
  {
    "ANNO": 2013,
    "CODICE_MESE": 4,
    "NOME_MESE": "Aprile",
    "CODICE_PRODOTTO": 1,
    "NOME_PRODOTTO": "Benzina",
    "PREZZO": "1753.8",
    "IVA": "304.38",
    "ACCISA": "728.4",
    "NETTO": "721.02"
  },
  {
    "ANNO": 2013,
    "CODICE_MESE": 5,
    "NOME_MESE": "Maggio",
    "CODICE_PRODOTTO": 1,
    "NOME_PRODOTTO": "Benzina",
    "PREZZO": "1716.16",
    "IVA": "297.85",
    "ACCISA": "728.4",
    "NETTO": "689.92"
  },
  {
    "ANNO": 2013,
    "CODICE_MESE": 6,
    "NOME_MESE": "Giugno",
    "CODICE_PRODOTTO": 1,
    "NOME_PRODOTTO": "Benzina",
    "PREZZO": "1733.76",
    "IVA": "300.9",
    "ACCISA": "728.4",
    "NETTO": "704.46"
  },
  {
    "ANNO": 2013,
    "CODICE_MESE": 7,
    "NOME_MESE": "Luglio",
    "CODICE_PRODOTTO": 1,
    "NOME_PRODOTTO": "Benzina",
    "PREZZO": "1753.53",
    "IVA": "304.33",
    "ACCISA": "728.4",
    "NETTO": "720.8"
  },
  {
    "ANNO": 2013,
    "CODICE_MESE": 8,
    "NOME_MESE": "Agosto",
    "CODICE_PRODOTTO": 1,
    "NOME_PRODOTTO": "Benzina",
    "PREZZO": "1767.85",
    "IVA": "306.82",
    "ACCISA": "728.4",
    "NETTO": "732.63"
  },
  {
    "ANNO": 2013,
    "CODICE_MESE": 9,
    "NOME_MESE": "Settembre",
    "CODICE_PRODOTTO": 1,
    "NOME_PRODOTTO": "Benzina",
    "PREZZO": "1773.23",
    "IVA": "307.75",
    "ACCISA": "728.4",
    "NETTO": "737.08"
  },
  {
    "ANNO": 2013,
    "CODICE_MESE": 10,
    "NOME_MESE": "Ottobre",
    "CODICE_PRODOTTO": 1,
    "NOME_PRODOTTO": "Benzina",
    "PREZZO": "1728.78",
    "IVA": "311.75",
    "ACCISA": "728.4",
    "NETTO": "688.63"
  },
  {
    "ANNO": 2013,
    "CODICE_MESE": 11,
    "NOME_MESE": "Novembre",
    "CODICE_PRODOTTO": 1,
    "NOME_PRODOTTO": "Benzina",
    "PREZZO": "1703.56",
    "IVA": "307.2",
    "ACCISA": "728.4",
    "NETTO": "667.96"
  },
  {
    "ANNO": 2013,
    "CODICE_MESE": 12,
    "NOME_MESE": "Dicembre",
    "CODICE_PRODOTTO": 1,
    "NOME_PRODOTTO": "Benzina",
    "PREZZO": "1727.63",
    "IVA": "311.54",
    "ACCISA": "728.4",
    "NETTO": "687.69"
  },
  {
    "ANNO": 2014,
    "CODICE_MESE": 1,
    "NOME_MESE": "Gennaio",
    "CODICE_PRODOTTO": 1,
    "NOME_PRODOTTO": "Benzina",
    "PREZZO": "1723.07",
    "IVA": "310.72",
    "ACCISA": "728.4",
    "NETTO": "683.95"
  },
  {
    "ANNO": 2014,
    "CODICE_MESE": 2,
    "NOME_MESE": "Febbraio",
    "CODICE_PRODOTTO": 1,
    "NOME_PRODOTTO": "Benzina",
    "PREZZO": "1714.05",
    "IVA": "309.09",
    "ACCISA": "728.4",
    "NETTO": "676.56"
  },
  {
    "ANNO": 2014,
    "CODICE_MESE": 3,
    "NOME_MESE": "Marzo",
    "CODICE_PRODOTTO": 1,
    "NOME_PRODOTTO": "Benzina",
    "PREZZO": "1715.3",
    "IVA": "309.32",
    "ACCISA": "730.8",
    "NETTO": "675.19"
  },
  {
    "ANNO": 2014,
    "CODICE_MESE": 4,
    "NOME_MESE": "Aprile",
    "CODICE_PRODOTTO": 1,
    "NOME_PRODOTTO": "Benzina",
    "PREZZO": "1725.6",
    "IVA": "311.17",
    "ACCISA": "730.8",
    "NETTO": "683.63"
  },
  {
    "ANNO": 2014,
    "CODICE_MESE": 5,
    "NOME_MESE": "Maggio",
    "CODICE_PRODOTTO": 1,
    "NOME_PRODOTTO": "Benzina",
    "PREZZO": "1737.53",
    "IVA": "313.32",
    "ACCISA": "730.8",
    "NETTO": "693.4"
  },
  {
    "ANNO": 2014,
    "CODICE_MESE": 6,
    "NOME_MESE": "Giugno",
    "CODICE_PRODOTTO": 1,
    "NOME_PRODOTTO": "Benzina",
    "PREZZO": "1743.96",
    "IVA": "314.49",
    "ACCISA": "730.8",
    "NETTO": "698.68"
  },
  {
    "ANNO": 2014,
    "CODICE_MESE": 7,
    "NOME_MESE": "Luglio",
    "CODICE_PRODOTTO": 1,
    "NOME_PRODOTTO": "Benzina",
    "PREZZO": "1761.19",
    "IVA": "317.59",
    "ACCISA": "730.8",
    "NETTO": "712.8"
  },
  {
    "ANNO": 2014,
    "CODICE_MESE": 8,
    "NOME_MESE": "Agosto",
    "CODICE_PRODOTTO": 1,
    "NOME_PRODOTTO": "Benzina",
    "PREZZO": "1749.73",
    "IVA": "315.52",
    "ACCISA": "730.8",
    "NETTO": "703.4"
  },
  {
    "ANNO": 2014,
    "CODICE_MESE": 9,
    "NOME_MESE": "Settembre",
    "CODICE_PRODOTTO": 1,
    "NOME_PRODOTTO": "Benzina",
    "PREZZO": "1734.56",
    "IVA": "312.79",
    "ACCISA": "730.8",
    "NETTO": "690.96"
  },
  {
    "ANNO": 2014,
    "CODICE_MESE": 10,
    "NOME_MESE": "Ottobre",
    "CODICE_PRODOTTO": 1,
    "NOME_PRODOTTO": "Benzina",
    "PREZZO": "1709.22",
    "IVA": "308.22",
    "ACCISA": "730.8",
    "NETTO": "670.2"
  },
  {
    "ANNO": 2014,
    "CODICE_MESE": 11,
    "NOME_MESE": "Novembre",
    "CODICE_PRODOTTO": 1,
    "NOME_PRODOTTO": "Benzina",
    "PREZZO": "1652.41",
    "IVA": "297.98",
    "ACCISA": "730.8",
    "NETTO": "623.64"
  },
  {
    "ANNO": 2014,
    "CODICE_MESE": 12,
    "NOME_MESE": "Dicembre",
    "CODICE_PRODOTTO": 1,
    "NOME_PRODOTTO": "Benzina",
    "PREZZO": "1585.65",
    "IVA": "285.94",
    "ACCISA": "730.8",
    "NETTO": "568.91"
  },
  {
    "ANNO": 2015,
    "CODICE_MESE": 1,
    "NOME_MESE": "Gennaio",
    "CODICE_PRODOTTO": 1,
    "NOME_PRODOTTO": "Benzina",
    "PREZZO": "1472.04",
    "IVA": "265.45",
    "ACCISA": "728.4",
    "NETTO": "478.19"
  },
  {
    "ANNO": 2015,
    "CODICE_MESE": 2,
    "NOME_MESE": "Febbraio",
    "CODICE_PRODOTTO": 1,
    "NOME_PRODOTTO": "Benzina",
    "PREZZO": "1489.44",
    "IVA": "268.59",
    "ACCISA": "728.4",
    "NETTO": "492.46"
  },
  {
    "ANNO": 2015,
    "CODICE_MESE": 3,
    "NOME_MESE": "Marzo",
    "CODICE_PRODOTTO": 1,
    "NOME_PRODOTTO": "Benzina",
    "PREZZO": "1565.9",
    "IVA": "282.38",
    "ACCISA": "728.4",
    "NETTO": "555.13"
  },
  {
    "ANNO": 2015,
    "CODICE_MESE": 4,
    "NOME_MESE": "Aprile",
    "CODICE_PRODOTTO": 1,
    "NOME_PRODOTTO": "Benzina",
    "PREZZO": "1580.63",
    "IVA": "285.03",
    "ACCISA": "728.4",
    "NETTO": "567.2"
  },
  {
    "ANNO": 2015,
    "CODICE_MESE": 5,
    "NOME_MESE": "Maggio",
    "CODICE_PRODOTTO": 1,
    "NOME_PRODOTTO": "Benzina",
    "PREZZO": "1614.05",
    "IVA": "291.06",
    "ACCISA": "728.4",
    "NETTO": "594.59"
  },
  {
    "ANNO": 2015,
    "CODICE_MESE": 6,
    "NOME_MESE": "Giugno",
    "CODICE_PRODOTTO": 1,
    "NOME_PRODOTTO": "Benzina",
    "PREZZO": "1622.84",
    "IVA": "292.64",
    "ACCISA": "728.4",
    "NETTO": "601.79"
  },
  {
    "ANNO": 2015,
    "CODICE_MESE": 7,
    "NOME_MESE": "Luglio",
    "CODICE_PRODOTTO": 1,
    "NOME_PRODOTTO": "Benzina",
    "PREZZO": "1625.46",
    "IVA": "293.12",
    "ACCISA": "728.4",
    "NETTO": "603.94"
  },
  {
    "ANNO": 2015,
    "CODICE_MESE": 8,
    "NOME_MESE": "Agosto",
    "CODICE_PRODOTTO": 1,
    "NOME_PRODOTTO": "Benzina",
    "PREZZO": "1567.82",
    "IVA": "282.72",
    "ACCISA": "728.4",
    "NETTO": "556.7"
  },
  {
    "ANNO": 2015,
    "CODICE_MESE": 9,
    "NOME_MESE": "Settembre",
    "CODICE_PRODOTTO": 1,
    "NOME_PRODOTTO": "Benzina",
    "PREZZO": "1494.74",
    "IVA": "269.54",
    "ACCISA": "728.4",
    "NETTO": "496.8"
  },
  {
    "ANNO": 2015,
    "CODICE_MESE": 10,
    "NOME_MESE": "Ottobre",
    "CODICE_PRODOTTO": 1,
    "NOME_PRODOTTO": "Benzina",
    "PREZZO": "1473.21",
    "IVA": "265.66",
    "ACCISA": "728.4",
    "NETTO": "479.15"
  },
  {
    "ANNO": 2015,
    "CODICE_MESE": 11,
    "NOME_MESE": "Novembre",
    "CODICE_PRODOTTO": 1,
    "NOME_PRODOTTO": "Benzina",
    "PREZZO": "1457.35",
    "IVA": "262.8",
    "ACCISA": "728.4",
    "NETTO": "466.14"
  },
  {
    "ANNO": 2015,
    "CODICE_MESE": 12,
    "NOME_MESE": "Dicembre",
    "CODICE_PRODOTTO": 1,
    "NOME_PRODOTTO": "Benzina",
    "PREZZO": "1450.68",
    "IVA": "261.6",
    "ACCISA": "728.4",
    "NETTO": "460.68"
  },
  {
    "ANNO": 2016,
    "CODICE_MESE": 1,
    "NOME_MESE": "Gennaio",
    "CODICE_PRODOTTO": 1,
    "NOME_PRODOTTO": "Benzina",
    "PREZZO": "1416.05",
    "IVA": "255.35",
    "ACCISA": "728.4",
    "NETTO": "432.3"
  },
  {
    "ANNO": 2016,
    "CODICE_MESE": 2,
    "NOME_MESE": "Febbraio",
    "CODICE_PRODOTTO": 1,
    "NOME_PRODOTTO": "Benzina",
    "PREZZO": "1378.18",
    "IVA": "248.53",
    "ACCISA": "728.4",
    "NETTO": "401.26"
  },
  {
    "ANNO": 2016,
    "CODICE_MESE": 3,
    "NOME_MESE": "Marzo",
    "CODICE_PRODOTTO": 1,
    "NOME_PRODOTTO": "Benzina",
    "PREZZO": "1388.15",
    "IVA": "250.32",
    "ACCISA": "728.4",
    "NETTO": "409.43"
  },
  {
    "ANNO": 2016,
    "CODICE_MESE": 4,
    "NOME_MESE": "Aprile",
    "CODICE_PRODOTTO": 1,
    "NOME_PRODOTTO": "Benzina",
    "PREZZO": "1420.94",
    "IVA": "256.23",
    "ACCISA": "728.4",
    "NETTO": "436.3"
  },
  {
    "ANNO": 2016,
    "CODICE_MESE": 5,
    "NOME_MESE": "Maggio",
    "CODICE_PRODOTTO": 1,
    "NOME_PRODOTTO": "Benzina",
    "PREZZO": "1452.65",
    "IVA": "261.96",
    "ACCISA": "728.4",
    "NETTO": "462.3"
  },
  {
    "ANNO": 2016,
    "CODICE_MESE": 6,
    "NOME_MESE": "Giugno",
    "CODICE_PRODOTTO": 1,
    "NOME_PRODOTTO": "Benzina",
    "PREZZO": "1479.16",
    "IVA": "266.74",
    "ACCISA": "728.4",
    "NETTO": "484.02"
  },
  {
    "ANNO": 2016,
    "CODICE_MESE": 7,
    "NOME_MESE": "Luglio",
    "CODICE_PRODOTTO": 1,
    "NOME_PRODOTTO": "Benzina",
    "PREZZO": "1456.54",
    "IVA": "262.65",
    "ACCISA": "728.4",
    "NETTO": "465.48"
  },
  {
    "ANNO": 2016,
    "CODICE_MESE": 8,
    "NOME_MESE": "Agosto",
    "CODICE_PRODOTTO": 1,
    "NOME_PRODOTTO": "Benzina",
    "PREZZO": "1433.05",
    "IVA": "258.42",
    "ACCISA": "728.4",
    "NETTO": "446.23"
  },
  {
    "ANNO": 2016,
    "CODICE_MESE": 9,
    "NOME_MESE": "Settembre",
    "CODICE_PRODOTTO": 1,
    "NOME_PRODOTTO": "Benzina",
    "PREZZO": "1453.71",
    "IVA": "262.15",
    "ACCISA": "728.4",
    "NETTO": "463.17"
  },
  {
    "ANNO": 2016,
    "CODICE_MESE": 10,
    "NOME_MESE": "Ottobre",
    "CODICE_PRODOTTO": 1,
    "NOME_PRODOTTO": "Benzina",
    "PREZZO": "1473.91",
    "IVA": "265.79",
    "ACCISA": "728.4",
    "NETTO": "479.73"
  },
  {
    "ANNO": 2016,
    "CODICE_MESE": 11,
    "NOME_MESE": "Novembre",
    "CODICE_PRODOTTO": 1,
    "NOME_PRODOTTO": "Benzina",
    "PREZZO": "1475.43",
    "IVA": "266.06",
    "ACCISA": "728.4",
    "NETTO": "480.97"
  },
  {
    "ANNO": 2016,
    "CODICE_MESE": 12,
    "NOME_MESE": "Dicembre",
    "CODICE_PRODOTTO": 1,
    "NOME_PRODOTTO": "Benzina",
    "PREZZO": "1495.98",
    "IVA": "269.76",
    "ACCISA": "728.4",
    "NETTO": "497.82"
  },
  {
    "ANNO": 2017,
    "CODICE_MESE": 1,
    "NOME_MESE": "Gennaio",
    "CODICE_PRODOTTO": 1,
    "NOME_PRODOTTO": "Benzina",
    "PREZZO": "1544.11",
    "IVA": "278.45",
    "ACCISA": "728.4",
    "NETTO": "537.27"
  },
  {
    "ANNO": 2017,
    "CODICE_MESE": 2,
    "NOME_MESE": "Febbraio",
    "CODICE_PRODOTTO": 1,
    "NOME_PRODOTTO": "Benzina",
    "PREZZO": "1549.83",
    "IVA": "279.48",
    "ACCISA": "728.4",
    "NETTO": "541.95"
  },
  {
    "ANNO": 2017,
    "CODICE_MESE": 3,
    "NOME_MESE": "Marzo",
    "CODICE_PRODOTTO": 1,
    "NOME_PRODOTTO": "Benzina",
    "PREZZO": "1540.37",
    "IVA": "277.77",
    "ACCISA": "728.4",
    "NETTO": "534.2"
  },
  {
    "ANNO": 2017,
    "CODICE_MESE": 4,
    "NOME_MESE": "Aprile",
    "CODICE_PRODOTTO": 1,
    "NOME_PRODOTTO": "Benzina",
    "PREZZO": "1551.38",
    "IVA": "279.76",
    "ACCISA": "728.4",
    "NETTO": "543.23"
  },
  {
    "ANNO": 2017,
    "CODICE_MESE": 5,
    "NOME_MESE": "Maggio",
    "CODICE_PRODOTTO": 1,
    "NOME_PRODOTTO": "Benzina",
    "PREZZO": "1528.5",
    "IVA": "275.63",
    "ACCISA": "728.4",
    "NETTO": "524.47"
  },
  {
    "ANNO": 2017,
    "CODICE_MESE": 6,
    "NOME_MESE": "Giugno",
    "CODICE_PRODOTTO": 1,
    "NOME_PRODOTTO": "Benzina",
    "PREZZO": "1501.94",
    "IVA": "270.84",
    "ACCISA": "728.4",
    "NETTO": "502.7"
  },
  {
    "ANNO": 2017,
    "CODICE_MESE": 7,
    "NOME_MESE": "Luglio",
    "CODICE_PRODOTTO": 1,
    "NOME_PRODOTTO": "Benzina",
    "PREZZO": "1490.63",
    "IVA": "268.8",
    "ACCISA": "728.4",
    "NETTO": "493.42"
  },
  {
    "ANNO": 2017,
    "CODICE_MESE": 8,
    "NOME_MESE": "Agosto",
    "CODICE_PRODOTTO": 1,
    "NOME_PRODOTTO": "Benzina",
    "PREZZO": "1499.93",
    "IVA": "270.48",
    "ACCISA": "728.4",
    "NETTO": "501.05"
  },
  {
    "ANNO": 2017,
    "CODICE_MESE": 9,
    "NOME_MESE": "Settembre",
    "CODICE_PRODOTTO": 1,
    "NOME_PRODOTTO": "Benzina",
    "PREZZO": "1522.28",
    "IVA": "274.51",
    "ACCISA": "728.4",
    "NETTO": "519.37"
  },
  {
    "ANNO": 2017,
    "CODICE_MESE": 10,
    "NOME_MESE": "Ottobre",
    "CODICE_PRODOTTO": 1,
    "NOME_PRODOTTO": "Benzina",
    "PREZZO": "1525.06",
    "IVA": "275.01",
    "ACCISA": "728.4",
    "NETTO": "521.65"
  },
  {
    "ANNO": 2017,
    "CODICE_MESE": 11,
    "NOME_MESE": "Novembre",
    "CODICE_PRODOTTO": 1,
    "NOME_PRODOTTO": "Benzina",
    "PREZZO": "1543.7",
    "IVA": "278.37",
    "ACCISA": "728.4",
    "NETTO": "536.92"
  },
  {
    "ANNO": 2017,
    "CODICE_MESE": 12,
    "NOME_MESE": "Dicembre",
    "CODICE_PRODOTTO": 1,
    "NOME_PRODOTTO": "Benzina",
    "PREZZO": "1550.04",
    "IVA": "279.52",
    "ACCISA": "728.4",
    "NETTO": "542.12"
  },
  {
    "ANNO": 2018,
    "CODICE_MESE": 1,
    "NOME_MESE": "Gennaio",
    "CODICE_PRODOTTO": 1,
    "NOME_PRODOTTO": "Benzina",
    "PREZZO": "1568.6",
    "IVA": "282.86",
    "ACCISA": "728.4",
    "NETTO": "557.34"
  },
  {
    "ANNO": 2018,
    "CODICE_MESE": 2,
    "NOME_MESE": "Febbraio",
    "CODICE_PRODOTTO": 1,
    "NOME_PRODOTTO": "Benzina",
    "PREZZO": "1558.25",
    "IVA": "281",
    "ACCISA": "728.4",
    "NETTO": "548.85"
  },
  {
    "ANNO": 2018,
    "CODICE_MESE": 3,
    "NOME_MESE": "Marzo",
    "CODICE_PRODOTTO": 1,
    "NOME_PRODOTTO": "Benzina",
    "PREZZO": "1547.96",
    "IVA": "279.14",
    "ACCISA": "728.4",
    "NETTO": "540.43"
  },
  {
    "ANNO": 2018,
    "CODICE_MESE": 4,
    "NOME_MESE": "Aprile",
    "CODICE_PRODOTTO": 1,
    "NOME_PRODOTTO": "Benzina",
    "PREZZO": "1569.69",
    "IVA": "283.06",
    "ACCISA": "728.4",
    "NETTO": "558.23"
  },
  {
    "ANNO": 2018,
    "CODICE_MESE": 5,
    "NOME_MESE": "Maggio",
    "CODICE_PRODOTTO": 1,
    "NOME_PRODOTTO": "Benzina",
    "PREZZO": "1621.03",
    "IVA": "292.32",
    "ACCISA": "728.4",
    "NETTO": "600.31"
  },
  {
    "ANNO": 2018,
    "CODICE_MESE": 6,
    "NOME_MESE": "Giugno",
    "CODICE_PRODOTTO": 1,
    "NOME_PRODOTTO": "Benzina",
    "PREZZO": "1641.66",
    "IVA": "296.04",
    "ACCISA": "728.4",
    "NETTO": "617.22"
  },
  {
    "ANNO": 2018,
    "CODICE_MESE": 7,
    "NOME_MESE": "Luglio",
    "CODICE_PRODOTTO": 1,
    "NOME_PRODOTTO": "Benzina",
    "PREZZO": "1630.46",
    "IVA": "294.02",
    "ACCISA": "728.4",
    "NETTO": "608.04"
  },
  {
    "ANNO": 2018,
    "CODICE_MESE": 8,
    "NOME_MESE": "Agosto",
    "CODICE_PRODOTTO": 1,
    "NOME_PRODOTTO": "Benzina",
    "PREZZO": "1629.52",
    "IVA": "293.85",
    "ACCISA": "728.4",
    "NETTO": "607.27"
  },
  {
    "ANNO": 2018,
    "CODICE_MESE": 9,
    "NOME_MESE": "Settembre",
    "CODICE_PRODOTTO": 1,
    "NOME_PRODOTTO": "Benzina",
    "PREZZO": "1642.2",
    "IVA": "296.13",
    "ACCISA": "728.4",
    "NETTO": "617.67"
  },
  {
    "ANNO": 2018,
    "CODICE_MESE": 10,
    "NOME_MESE": "Ottobre",
    "CODICE_PRODOTTO": 1,
    "NOME_PRODOTTO": "Benzina",
    "PREZZO": "1658.86",
    "IVA": "299.14",
    "ACCISA": "728.4",
    "NETTO": "631.32"
  },
  {
    "ANNO": 2018,
    "CODICE_MESE": 11,
    "NOME_MESE": "Novembre",
    "CODICE_PRODOTTO": 1,
    "NOME_PRODOTTO": "Benzina",
    "PREZZO": "1612.9",
    "IVA": "290.85",
    "ACCISA": "728.4",
    "NETTO": "593.65"
  },
  {
    "ANNO": 2018,
    "CODICE_MESE": 12,
    "NOME_MESE": "Dicembre",
    "CODICE_PRODOTTO": 1,
    "NOME_PRODOTTO": "Benzina",
    "PREZZO": "1509.6",
    "IVA": "272.22",
    "ACCISA": "728.4",
    "NETTO": "508.98"
  },
  {
    "ANNO": 2019,
    "CODICE_MESE": 1,
    "NOME_MESE": "Gennaio",
    "CODICE_PRODOTTO": 1,
    "NOME_PRODOTTO": "Benzina",
    "PREZZO": "1490.13",
    "IVA": "268.71",
    "ACCISA": "728.4",
    "NETTO": "493.02"
  },
  {
    "ANNO": 2019,
    "CODICE_MESE": 2,
    "NOME_MESE": "Febbraio",
    "CODICE_PRODOTTO": 1,
    "NOME_PRODOTTO": "Benzina",
    "PREZZO": "1521.15",
    "IVA": "274.31",
    "ACCISA": "728.4",
    "NETTO": "518.44"
  },
  {
    "ANNO": 2019,
    "CODICE_MESE": 3,
    "NOME_MESE": "Marzo",
    "CODICE_PRODOTTO": 1,
    "NOME_PRODOTTO": "Benzina",
    "PREZZO": "1558.09",
    "IVA": "280.97",
    "ACCISA": "728.4",
    "NETTO": "548.72"
  },
  {
    "ANNO": 2019,
    "CODICE_MESE": 4,
    "NOME_MESE": "Aprile",
    "CODICE_PRODOTTO": 1,
    "NOME_PRODOTTO": "Benzina",
    "PREZZO": "1609.87",
    "IVA": "290.3",
    "ACCISA": "728.4",
    "NETTO": "591.17"
  },
  {
    "ANNO": 2019,
    "CODICE_MESE": 5,
    "NOME_MESE": "Maggio",
    "CODICE_PRODOTTO": 1,
    "NOME_PRODOTTO": "Benzina",
    "PREZZO": "1626.34",
    "IVA": "293.27",
    "ACCISA": "728.4",
    "NETTO": "604.67"
  },
  {
    "ANNO": 2019,
    "CODICE_MESE": 6,
    "NOME_MESE": "Giugno",
    "CODICE_PRODOTTO": 1,
    "NOME_PRODOTTO": "Benzina",
    "PREZZO": "1596.91",
    "IVA": "287.97",
    "ACCISA": "728.4",
    "NETTO": "580.54"
  },
  {
    "ANNO": 2019,
    "CODICE_MESE": 7,
    "NOME_MESE": "Luglio",
    "CODICE_PRODOTTO": 1,
    "NOME_PRODOTTO": "Benzina",
    "PREZZO": "1594.54",
    "IVA": "287.54",
    "ACCISA": "728.4",
    "NETTO": "578.6"
  },
  {
    "ANNO": 2019,
    "CODICE_MESE": 8,
    "NOME_MESE": "Agosto",
    "CODICE_PRODOTTO": 1,
    "NOME_PRODOTTO": "Benzina",
    "PREZZO": "1574.47",
    "IVA": "283.92",
    "ACCISA": "728.4",
    "NETTO": "562.15"
  },
  {
    "ANNO": 2019,
    "CODICE_MESE": 9,
    "NOME_MESE": "Settembre",
    "CODICE_PRODOTTO": 1,
    "NOME_PRODOTTO": "Benzina",
    "PREZZO": "1579.09",
    "IVA": "284.75",
    "ACCISA": "728.4",
    "NETTO": "565.94"
  },
  {
    "ANNO": 2019,
    "CODICE_MESE": 10,
    "NOME_MESE": "Ottobre",
    "CODICE_PRODOTTO": 1,
    "NOME_PRODOTTO": "Benzina",
    "PREZZO": "1576.79",
    "IVA": "284.34",
    "ACCISA": "728.4",
    "NETTO": "564.05"
  },
  {
    "ANNO": 2019,
    "CODICE_MESE": 11,
    "NOME_MESE": "Novembre",
    "CODICE_PRODOTTO": 1,
    "NOME_PRODOTTO": "Benzina",
    "PREZZO": "1575.67",
    "IVA": "284.14",
    "ACCISA": "728.4",
    "NETTO": "563.13"
  },
  {
    "ANNO": 2019,
    "CODICE_MESE": 12,
    "NOME_MESE": "Dicembre",
    "CODICE_PRODOTTO": 1,
    "NOME_PRODOTTO": "Benzina",
    "PREZZO": "1584.91",
    "IVA": "285.81",
    "ACCISA": "728.4",
    "NETTO": "570.7"
  },
  {
    "ANNO": 2020,
    "CODICE_MESE": 1,
    "NOME_MESE": "Gennaio",
    "CODICE_PRODOTTO": 1,
    "NOME_PRODOTTO": "Benzina",
    "PREZZO": "1586.42",
    "IVA": "286.08",
    "ACCISA": "728.4",
    "NETTO": "571.94"
  },
  {
    "ANNO": 2020,
    "CODICE_MESE": 2,
    "NOME_MESE": "Febbraio",
    "CODICE_PRODOTTO": 1,
    "NOME_PRODOTTO": "Benzina",
    "PREZZO": "1548.73",
    "IVA": "279.28",
    "ACCISA": "728.4",
    "NETTO": "541.05"
  },
  {
    "ANNO": 2020,
    "CODICE_MESE": 3,
    "NOME_MESE": "Marzo",
    "CODICE_PRODOTTO": 1,
    "NOME_PRODOTTO": "Benzina",
    "PREZZO": "1486.59",
    "IVA": "268.07",
    "ACCISA": "728.4",
    "NETTO": "490.12"
  },
  {
    "ANNO": 2020,
    "CODICE_MESE": 4,
    "NOME_MESE": "Aprile",
    "CODICE_PRODOTTO": 1,
    "NOME_PRODOTTO": "Benzina",
    "PREZZO": "1408.57",
    "IVA": "254.01",
    "ACCISA": "728.4",
    "NETTO": "426.16"
  },
  {
    "ANNO": 2020,
    "CODICE_MESE": 5,
    "NOME_MESE": "Maggio",
    "CODICE_PRODOTTO": 1,
    "NOME_PRODOTTO": "Benzina",
    "PREZZO": "1365.22",
    "IVA": "246.19",
    "ACCISA": "728.4",
    "NETTO": "390.63"
  },
  {
    "ANNO": 2020,
    "CODICE_MESE": 6,
    "NOME_MESE": "Giugno",
    "CODICE_PRODOTTO": 1,
    "NOME_PRODOTTO": "Benzina",
    "PREZZO": "1384.5",
    "IVA": "249.66",
    "ACCISA": "728.4",
    "NETTO": "406.44"
  },
  {
    "ANNO": 2020,
    "CODICE_MESE": 7,
    "NOME_MESE": "Luglio",
    "CODICE_PRODOTTO": 1,
    "NOME_PRODOTTO": "Benzina",
    "PREZZO": "1403.1",
    "IVA": "253.02",
    "ACCISA": "728.4",
    "NETTO": "421.68"
  },
  {
    "ANNO": 2020,
    "CODICE_MESE": 8,
    "NOME_MESE": "Agosto",
    "CODICE_PRODOTTO": 1,
    "NOME_PRODOTTO": "Benzina",
    "PREZZO": "1399.08",
    "IVA": "252.29",
    "ACCISA": "728.4",
    "NETTO": "418.39"
  },
  {
    "ANNO": 2020,
    "CODICE_MESE": 9,
    "NOME_MESE": "Settembre",
    "CODICE_PRODOTTO": 1,
    "NOME_PRODOTTO": "Benzina",
    "PREZZO": "1391.59",
    "IVA": "250.94",
    "ACCISA": "728.4",
    "NETTO": "412.25"
  },
  {
    "ANNO": 2020,
    "CODICE_MESE": 10,
    "NOME_MESE": "Ottobre",
    "CODICE_PRODOTTO": 1,
    "NOME_PRODOTTO": "Benzina",
    "PREZZO": "1387.57",
    "IVA": "250.22",
    "ACCISA": "728.4",
    "NETTO": "408.95"
  },
  {
    "ANNO": 2020,
    "CODICE_MESE": 11,
    "NOME_MESE": "Novembre",
    "CODICE_PRODOTTO": 1,
    "NOME_PRODOTTO": "Benzina",
    "PREZZO": "1390.59",
    "IVA": "250.76",
    "ACCISA": "728.4",
    "NETTO": "411.43"
  },
  {
    "ANNO": 2020,
    "CODICE_MESE": 12,
    "NOME_MESE": "Dicembre",
    "CODICE_PRODOTTO": 1,
    "NOME_PRODOTTO": "Benzina",
    "PREZZO": "1423.91",
    "IVA": "256.77",
    "ACCISA": "728.4",
    "NETTO": "438.74"
  },
  {
    "ANNO": 2021,
    "CODICE_MESE": 1,
    "NOME_MESE": "Gennaio",
    "CODICE_PRODOTTO": 1,
    "NOME_PRODOTTO": "Benzina",
    "PREZZO": "1465.48",
    "IVA": "264.27",
    "ACCISA": "728.4",
    "NETTO": "472.81"
  },
  {
    "ANNO": 2021,
    "CODICE_MESE": 2,
    "NOME_MESE": "Febbraio",
    "CODICE_PRODOTTO": 1,
    "NOME_PRODOTTO": "Benzina",
    "PREZZO": "1511.12",
    "IVA": "272.5",
    "ACCISA": "728.4",
    "NETTO": "510.22"
  },
  {
    "ANNO": 2021,
    "CODICE_MESE": 3,
    "NOME_MESE": "Marzo",
    "CODICE_PRODOTTO": 1,
    "NOME_PRODOTTO": "Benzina",
    "PREZZO": "1568.13",
    "IVA": "282.78",
    "ACCISA": "728.4",
    "NETTO": "556.95"
  },
  {
    "ANNO": 2021,
    "CODICE_MESE": 4,
    "NOME_MESE": "Aprile",
    "CODICE_PRODOTTO": 1,
    "NOME_PRODOTTO": "Benzina",
    "PREZZO": "1575.55",
    "IVA": "284.12",
    "ACCISA": "728.4",
    "NETTO": "563.03"
  },
  {
    "ANNO": 2021,
    "CODICE_MESE": 5,
    "NOME_MESE": "Maggio",
    "CODICE_PRODOTTO": 1,
    "NOME_PRODOTTO": "Benzina",
    "PREZZO": "1590.33",
    "IVA": "286.78",
    "ACCISA": "728.4",
    "NETTO": "575.15"
  },
  {
    "ANNO": 2021,
    "CODICE_MESE": 6,
    "NOME_MESE": "Giugno",
    "CODICE_PRODOTTO": 1,
    "NOME_PRODOTTO": "Benzina",
    "PREZZO": "1613.63",
    "IVA": "290.98",
    "ACCISA": "728.4",
    "NETTO": "594.25"
  },
  {
    "ANNO": 2021,
    "CODICE_MESE": 7,
    "NOME_MESE": "Luglio",
    "CODICE_PRODOTTO": 1,
    "NOME_PRODOTTO": "Benzina",
    "PREZZO": "1650.96",
    "IVA": "297.72",
    "ACCISA": "728.4",
    "NETTO": "624.84"
  },
  {
    "ANNO": 2021,
    "CODICE_MESE": 8,
    "NOME_MESE": "Agosto",
    "CODICE_PRODOTTO": 1,
    "NOME_PRODOTTO": "Benzina",
    "PREZZO": "1654.17",
    "IVA": "298.29",
    "ACCISA": "728.4",
    "NETTO": "627.48"
  },
  {
    "ANNO": 2021,
    "CODICE_MESE": 9,
    "NOME_MESE": "Settembre",
    "CODICE_PRODOTTO": 1,
    "NOME_PRODOTTO": "Benzina",
    "PREZZO": "1669.58",
    "IVA": "301.07",
    "ACCISA": "728.4",
    "NETTO": "640.11"
  },
  {
    "ANNO": 2021,
    "CODICE_MESE": 10,
    "NOME_MESE": "Ottobre",
    "CODICE_PRODOTTO": 1,
    "NOME_PRODOTTO": "Benzina",
    "PREZZO": "1730.8",
    "IVA": "312.11",
    "ACCISA": "728.4",
    "NETTO": "690.29"
  },
  {
    "ANNO": 2021,
    "CODICE_MESE": 11,
    "NOME_MESE": "Novembre",
    "CODICE_PRODOTTO": 1,
    "NOME_PRODOTTO": "Benzina",
    "PREZZO": "1746.52",
    "IVA": "314.94",
    "ACCISA": "728.4",
    "NETTO": "703.18"
  },
  {
    "ANNO": 2021,
    "CODICE_MESE": 12,
    "NOME_MESE": "Dicembre",
    "CODICE_PRODOTTO": 1,
    "NOME_PRODOTTO": "Benzina",
    "PREZZO": "1724.25",
    "IVA": "310.93",
    "ACCISA": "728.4",
    "NETTO": "684.92"
  },
  {
    "ANNO": 2022,
    "CODICE_MESE": 1,
    "NOME_MESE": "Gennaio",
    "CODICE_PRODOTTO": 1,
    "NOME_PRODOTTO": "Benzina",
    "PREZZO": "1764.74",
    "IVA": "318.23",
    "ACCISA": "728.4",
    "NETTO": "718.11"
  },
  {
    "ANNO": 2022,
    "CODICE_MESE": 2,
    "NOME_MESE": "Febbraio",
    "CODICE_PRODOTTO": 1,
    "NOME_PRODOTTO": "Benzina",
    "PREZZO": "1848.12",
    "IVA": "333.27",
    "ACCISA": "728.4",
    "NETTO": "786.45"
  },
  {
    "ANNO": 2022,
    "CODICE_MESE": 3,
    "NOME_MESE": "Marzo",
    "CODICE_PRODOTTO": 1,
    "NOME_PRODOTTO": "Benzina",
    "PREZZO": "2007.59",
    "IVA": "362.02",
    "ACCISA": "639.69",
    "NETTO": "1005.88"
  },
  {
    "ANNO": 2022,
    "CODICE_MESE": 4,
    "NOME_MESE": "Aprile",
    "CODICE_PRODOTTO": 1,
    "NOME_PRODOTTO": "Benzina",
    "PREZZO": "1769",
    "IVA": "319",
    "ACCISA": "478.4",
    "NETTO": "971.6"
  },
  {
    "ANNO": 2022,
    "CODICE_MESE": 5,
    "NOME_MESE": "Maggio",
    "CODICE_PRODOTTO": 1,
    "NOME_PRODOTTO": "Benzina",
    "PREZZO": "1851.27",
    "IVA": "333.83",
    "ACCISA": "478.4",
    "NETTO": "1039.04"
  },
  {
    "ANNO": 2022,
    "CODICE_MESE": 6,
    "NOME_MESE": "Giugno",
    "CODICE_PRODOTTO": 1,
    "NOME_PRODOTTO": "Benzina",
    "PREZZO": "2034.16",
    "IVA": "366.82",
    "ACCISA": "478.4",
    "NETTO": "1188.94"
  },
  {
    "ANNO": 2022,
    "CODICE_MESE": 7,
    "NOME_MESE": "Luglio",
    "CODICE_PRODOTTO": 1,
    "NOME_PRODOTTO": "Benzina",
    "PREZZO": "1968.31",
    "IVA": "354.94",
    "ACCISA": "478.4",
    "NETTO": "1134.97"
  },
  {
    "ANNO": 2022,
    "CODICE_MESE": 8,
    "NOME_MESE": "Agosto",
    "CODICE_PRODOTTO": 1,
    "NOME_PRODOTTO": "Benzina",
    "PREZZO": "1774.87",
    "IVA": "320.06",
    "ACCISA": "478.4",
    "NETTO": "976.41"
  },
  {
    "ANNO": 2022,
    "CODICE_MESE": 9,
    "NOME_MESE": "Settembre",
    "CODICE_PRODOTTO": 1,
    "NOME_PRODOTTO": "Benzina",
    "PREZZO": "1687.97",
    "IVA": "304.39",
    "ACCISA": "478.4",
    "NETTO": "905.18"
  },
  {
    "ANNO": 2022,
    "CODICE_MESE": 10,
    "NOME_MESE": "Ottobre",
    "CODICE_PRODOTTO": 1,
    "NOME_PRODOTTO": "Benzina",
    "PREZZO": "1678.64",
    "IVA": "302.7",
    "ACCISA": "478.4",
    "NETTO": "897.54"
  },
  {
    "ANNO": 2022,
    "CODICE_MESE": 11,
    "NOME_MESE": "Novembre",
    "CODICE_PRODOTTO": 1,
    "NOME_PRODOTTO": "Benzina",
    "PREZZO": "1688.75",
    "IVA": "304.53",
    "ACCISA": "478.4",
    "NETTO": "905.82"
  },
  {
    "ANNO": 2022,
    "CODICE_MESE": 12,
    "NOME_MESE": "Dicembre",
    "CODICE_PRODOTTO": 1,
    "NOME_PRODOTTO": "Benzina",
    "PREZZO": "1662.93",
    "IVA": "299.87",
    "ACCISA": "578.4",
    "NETTO": "784.66"
  },
  {
    "ANNO": 2023,
    "CODICE_MESE": 1,
    "NOME_MESE": "Gennaio",
    "CODICE_PRODOTTO": 1,
    "NOME_PRODOTTO": "Benzina",
    "PREZZO": "1833.59",
    "IVA": "330.65",
    "ACCISA": "728.4",
    "NETTO": "774.54"
  },
  {
    "ANNO": 2023,
    "CODICE_MESE": 2,
    "NOME_MESE": "Febbraio",
    "CODICE_PRODOTTO": 1,
    "NOME_PRODOTTO": "Benzina",
    "PREZZO": "1860.75",
    "IVA": "335.54",
    "ACCISA": "728.4",
    "NETTO": "796.81"
  },
  {
    "ANNO": 2023,
    "CODICE_MESE": 3,
    "NOME_MESE": "Marzo",
    "CODICE_PRODOTTO": 1,
    "NOME_PRODOTTO": "Benzina",
    "PREZZO": "1855.41",
    "IVA": "334.58",
    "ACCISA": "728.4",
    "NETTO": "792.43"
  },
  {
    "ANNO": 2023,
    "CODICE_MESE": 4,
    "NOME_MESE": "Aprile",
    "CODICE_PRODOTTO": 1,
    "NOME_PRODOTTO": "Benzina",
    "PREZZO": "1873.05",
    "IVA": "337.77",
    "ACCISA": "728.4",
    "NETTO": "806.88"
  },
  {
    "ANNO": 2023,
    "CODICE_MESE": 5,
    "NOME_MESE": "Maggio",
    "CODICE_PRODOTTO": 1,
    "NOME_PRODOTTO": "Benzina",
    "PREZZO": "1818.49",
    "IVA": "327.92",
    "ACCISA": "728.4",
    "NETTO": "762.17"
  },
  {
    "ANNO": 2023,
    "CODICE_MESE": 6,
    "NOME_MESE": "Giugno",
    "CODICE_PRODOTTO": 1,
    "NOME_PRODOTTO": "Benzina",
    "PREZZO": "1839.84",
    "IVA": "331.77",
    "ACCISA": "728.4",
    "NETTO": "779.67"
  },
  {
    "ANNO": 2023,
    "CODICE_MESE": 7,
    "NOME_MESE": "Luglio",
    "CODICE_PRODOTTO": 1,
    "NOME_PRODOTTO": "Benzina",
    "PREZZO": "1867.33",
    "IVA": "336.73",
    "ACCISA": "728.4",
    "NETTO": "802.2"
  },
  {
    "ANNO": 2023,
    "CODICE_MESE": 8,
    "NOME_MESE": "Agosto",
    "CODICE_PRODOTTO": 1,
    "NOME_PRODOTTO": "Benzina",
    "PREZZO": "1942.71",
    "IVA": "350.33",
    "ACCISA": "728.4",
    "NETTO": "863.98"
  },
  {
    "ANNO": 2023,
    "CODICE_MESE": 9,
    "NOME_MESE": "Settembre",
    "CODICE_PRODOTTO": 1,
    "NOME_PRODOTTO": "Benzina",
    "PREZZO": "1986.48",
    "IVA": "358.22",
    "ACCISA": "728.4",
    "NETTO": "899.86"
  },
  {
    "ANNO": 2023,
    "CODICE_MESE": 10,
    "NOME_MESE": "Ottobre",
    "CODICE_PRODOTTO": 1,
    "NOME_PRODOTTO": "Benzina",
    "PREZZO": "1911.22",
    "IVA": "344.65",
    "ACCISA": "728.4",
    "NETTO": "838.17"
  },
  {
    "ANNO": 2023,
    "CODICE_MESE": 11,
    "NOME_MESE": "Novembre",
    "CODICE_PRODOTTO": 1,
    "NOME_PRODOTTO": "Benzina",
    "PREZZO": "1821.7",
    "IVA": "328.5",
    "ACCISA": "728.4",
    "NETTO": "764.8"
  },
  {
    "ANNO": 2023,
    "CODICE_MESE": 12,
    "NOME_MESE": "Dicembre",
    "CODICE_PRODOTTO": 1,
    "NOME_PRODOTTO": "Benzina",
    "PREZZO": "1773.26",
    "IVA": "319.77",
    "ACCISA": "728.4",
    "NETTO": "725.09"
  },
  {
    "ANNO": 2024,
    "CODICE_MESE": 1,
    "NOME_MESE": "Gennaio",
    "CODICE_PRODOTTO": 1,
    "NOME_PRODOTTO": "Benzina",
    "PREZZO": "1787.29",
    "IVA": "322.3",
    "ACCISA": "728.4",
    "NETTO": "736.59"
  },
  {
    "ANNO": 2024,
    "CODICE_MESE": 2,
    "NOME_MESE": "Febbraio",
    "CODICE_PRODOTTO": 1,
    "NOME_PRODOTTO": "Benzina",
    "PREZZO": "1850.16",
    "IVA": "333.63",
    "ACCISA": "728.4",
    "NETTO": "788.13"
  },
  {
    "ANNO": 2024,
    "CODICE_MESE": 3,
    "NOME_MESE": "Marzo",
    "CODICE_PRODOTTO": 1,
    "NOME_PRODOTTO": "Benzina",
    "PREZZO": "1865.66",
    "IVA": "336.43",
    "ACCISA": "728.4",
    "NETTO": "800.83"
  },
  {
    "ANNO": 2024,
    "CODICE_MESE": 4,
    "NOME_MESE": "Aprile",
    "CODICE_PRODOTTO": 1,
    "NOME_PRODOTTO": "Benzina",
    "PREZZO": "1912.4",
    "IVA": "344.86",
    "ACCISA": "728.4",
    "NETTO": "839.14"
  },
  {
    "ANNO": 2024,
    "CODICE_MESE": 5,
    "NOME_MESE": "Maggio",
    "CODICE_PRODOTTO": 1,
    "NOME_PRODOTTO": "Benzina",
    "PREZZO": "1886.28",
    "IVA": "340.15",
    "ACCISA": "728.4",
    "NETTO": "817.73"
  },
  {
    "ANNO": 2024,
    "CODICE_MESE": 6,
    "NOME_MESE": "Giugno",
    "CODICE_PRODOTTO": 1,
    "NOME_PRODOTTO": "Benzina",
    "PREZZO": "1851.11",
    "IVA": "333.81",
    "ACCISA": "728.4",
    "NETTO": "788.9"
  },
  {
    "ANNO": 2024,
    "CODICE_MESE": 7,
    "NOME_MESE": "Luglio",
    "CODICE_PRODOTTO": 1,
    "NOME_PRODOTTO": "Benzina",
    "PREZZO": "1861.31",
    "IVA": "335.64",
    "ACCISA": "728.4",
    "NETTO": "797.27"
  },
  {
    "ANNO": 2024,
    "CODICE_MESE": 8,
    "NOME_MESE": "Agosto",
    "CODICE_PRODOTTO": 1,
    "NOME_PRODOTTO": "Benzina",
    "PREZZO": "1817.95",
    "IVA": "327.83",
    "ACCISA": "728.4",
    "NETTO": "761.72"
  },
  {
    "ANNO": 2024,
    "CODICE_MESE": 9,
    "NOME_MESE": "Settembre",
    "CODICE_PRODOTTO": 1,
    "NOME_PRODOTTO": "Benzina",
    "PREZZO": "1755.48",
    "IVA": "316.56",
    "ACCISA": "728.4",
    "NETTO": "710.52"
  },
  {
    "ANNO": 2024,
    "CODICE_MESE": 10,
    "NOME_MESE": "Ottobre",
    "CODICE_PRODOTTO": 1,
    "NOME_PRODOTTO": "Benzina",
    "PREZZO": "1755.12",
    "IVA": "316.5",
    "ACCISA": "728.4",
    "NETTO": "710.22"
  },
  {
    "ANNO": 2024,
    "CODICE_MESE": 11,
    "NOME_MESE": "Novembre",
    "CODICE_PRODOTTO": 1,
    "NOME_PRODOTTO": "Benzina",
    "PREZZO": "1757.68",
    "IVA": "316.96",
    "ACCISA": "728.4",
    "NETTO": "712.32"
  },
  {
    "ANNO": 2024,
    "CODICE_MESE": 12,
    "NOME_MESE": "Dicembre",
    "CODICE_PRODOTTO": 1,
    "NOME_PRODOTTO": "Benzina",
    "PREZZO": "1756.14",
    "IVA": "316.68",
    "ACCISA": "728.4",
    "NETTO": "711.06"
  }
]